{
  "id": "V2At0Z7gcRc-uHEuMrYVO",
  "name": "Hello Kinopio",
  "privacy": "private",
  "showInExplore": false,
  "collaboratorKey": "oo4dSsrnK_cjW7FRD7anN",
  "collaborators": [],
  "spectators": [],
  "background": "https://bk.kinopio.club/squiggle-background-2x.png",
  "backgroundTint": "",
  "backgroundGradient": null,
  "backgroundIsGradient": false,
  "isTemplate": false,
  "cards": [
    {
      "id": "st9tjJlIdwa6iZplQ74ni",
      "x": 784,
      "y": 1592,
      "z": 2530,
      "name": "https://kinopio.club/-inspiration--PvOMf-lSAIAC9INOu8_Ex ",
      "frameId": 0,
      "isRemoved": false,
      "nameUpdatedAt": "2026-01-12T20:38:42.867Z",
      "nameUpdatedByUserId": "euGhpBrR9eBcjKnK16C_g",
      "linkToSpaceId": "PvOMf-lSAIAC9INOu8_Ex",
      "linkToSpaceCollaboratorKey": null,
      "urlPreviewIsVisible": true,
      "shouldShowOtherSpacePreviewImage": true,
      "shouldHideUrlPreviewInfo": false,
      "shouldHideUrlPreviewImage": false,
      "shouldUpdateUrlPreview": false,
      "isLocked": false,
      "isComment": false,
      "isTodo": false,
      "urlIsVisible": false,
      "urlPreviewUrl": null,
      "urlPreviewImage": null,
      "urlPreviewFavicon": null,
      "urlPreviewTitle": null,
      "urlPreviewDescription": null,
      "urlPreviewErrorUrl": null,
      "urlPreviewEmbedHtml": null,
      "urlPreviewIframeUrl": null,
      "backgroundColor": null,
      "resizeWidth": null,
      "isCreatedThroughPublicApi": true,
      "counterIsVisible": false,
      "counterValue": 0,
      "codeBlockLanguage": null,
      "width": 200,
      "height": 165,
      "tilt": 0,
      "maxWidth": 200,
      "headerFontId": 0,
      "headerFontSize": "s",
      "createdAt": "2026-01-12T20:38:39.050Z",
      "updatedAt": "2026-01-13T00:14:53.439Z",
      "spaceId": "V2At0Z7gcRc-uHEuMrYVO",
      "userId": "84tJq5nDb6RSP9qIPqsYs",
      "linkToCardId": null
    },
    {
      "id": "FN2JSqJ_9LpmxIX5tu7Oe",
      "x": 112,
      "y": 1592,
      "z": 2520,
      "name": "https://kinopio.club/roadmap-3CBHtivu7X7nTzrcaTFQV ",
      "frameId": 0,
      "isRemoved": false,
      "nameUpdatedAt": "2023-07-15T23:07:57.082Z",
      "nameUpdatedByUserId": null,
      "linkToSpaceId": "3CBHtivu7X7nTzrcaTFQV",
      "linkToSpaceCollaboratorKey": null,
      "urlPreviewIsVisible": true,
      "shouldShowOtherSpacePreviewImage": true,
      "shouldHideUrlPreviewInfo": false,
      "shouldHideUrlPreviewImage": false,
      "shouldUpdateUrlPreview": false,
      "isLocked": false,
      "isComment": false,
      "isTodo": null,
      "urlIsVisible": false,
      "urlPreviewUrl": null,
      "urlPreviewImage": null,
      "urlPreviewFavicon": null,
      "urlPreviewTitle": null,
      "urlPreviewDescription": null,
      "urlPreviewErrorUrl": null,
      "urlPreviewEmbedHtml": null,
      "urlPreviewIframeUrl": null,
      "backgroundColor": null,
      "resizeWidth": 0,
      "isCreatedThroughPublicApi": true,
      "counterIsVisible": false,
      "counterValue": 0,
      "codeBlockLanguage": null,
      "width": 200,
      "height": 165,
      "tilt": 0,
      "maxWidth": null,
      "headerFontId": 0,
      "headerFontSize": "s",
      "createdAt": "2023-07-15T22:48:58.688Z",
      "updatedAt": "2026-01-13T00:14:53.528Z",
      "spaceId": "V2At0Z7gcRc-uHEuMrYVO",
      "userId": "84tJq5nDb6RSP9qIPqsYs",
      "linkToCardId": null
    },
    {
      "id": "A8hs-KUj_63BhelxvAJE6",
      "x": 336,
      "y": 1592,
      "z": 2522,
      "name": "https://kinopio.club/computing-happiness-SrLvfAPsBIsor4g9iIW7D\n",
      "frameId": 0,
      "isRemoved": false,
      "nameUpdatedAt": "2023-07-15T23:07:57.095Z",
      "nameUpdatedByUserId": null,
      "linkToSpaceId": "SrLvfAPsBIsor4g9iIW7D",
      "linkToSpaceCollaboratorKey": null,
      "urlPreviewIsVisible": true,
      "shouldShowOtherSpacePreviewImage": true,
      "shouldHideUrlPreviewInfo": false,
      "shouldHideUrlPreviewImage": false,
      "shouldUpdateUrlPreview": false,
      "isLocked": false,
      "isComment": false,
      "isTodo": false,
      "urlIsVisible": false,
      "urlPreviewUrl": null,
      "urlPreviewImage": null,
      "urlPreviewFavicon": null,
      "urlPreviewTitle": null,
      "urlPreviewDescription": null,
      "urlPreviewErrorUrl": null,
      "urlPreviewEmbedHtml": null,
      "urlPreviewIframeUrl": null,
      "backgroundColor": null,
      "resizeWidth": 0,
      "isCreatedThroughPublicApi": true,
      "counterIsVisible": false,
      "counterValue": 0,
      "codeBlockLanguage": null,
      "width": 200,
      "height": 183,
      "tilt": 0,
      "maxWidth": null,
      "headerFontId": 0,
      "headerFontSize": "s",
      "createdAt": "2023-07-15T22:47:46.082Z",
      "updatedAt": "2026-01-13T00:14:53.576Z",
      "spaceId": "V2At0Z7gcRc-uHEuMrYVO",
      "userId": "84tJq5nDb6RSP9qIPqsYs",
      "linkToCardId": null
    },
    {
      "id": "_Ayjw_r9esWFddAav1np6",
      "x": 560,
      "y": 1592,
      "z": 2526,
      "name": "https://kinopio.club/kinopio-architecture-and-costs-JOGXFJ0FEMpS3crbh6U9k",
      "frameId": null,
      "isRemoved": false,
      "nameUpdatedAt": "2023-07-15T23:07:57.143Z",
      "nameUpdatedByUserId": null,
      "linkToSpaceId": "JOGXFJ0FEMpS3crbh6U9k",
      "linkToSpaceCollaboratorKey": null,
      "urlPreviewIsVisible": true,
      "shouldShowOtherSpacePreviewImage": true,
      "shouldHideUrlPreviewInfo": false,
      "shouldHideUrlPreviewImage": false,
      "shouldUpdateUrlPreview": false,
      "isLocked": false,
      "isComment": false,
      "isTodo": false,
      "urlIsVisible": false,
      "urlPreviewUrl": null,
      "urlPreviewImage": null,
      "urlPreviewFavicon": null,
      "urlPreviewTitle": null,
      "urlPreviewDescription": null,
      "urlPreviewErrorUrl": null,
      "urlPreviewEmbedHtml": null,
      "urlPreviewIframeUrl": null,
      "backgroundColor": null,
      "resizeWidth": 0,
      "isCreatedThroughPublicApi": true,
      "counterIsVisible": false,
      "counterValue": 1,
      "codeBlockLanguage": null,
      "width": 200,
      "height": 183,
      "tilt": 0,
      "maxWidth": null,
      "headerFontId": 0,
      "headerFontSize": "s",
      "createdAt": "2022-07-18T21:47:24.153Z",
      "updatedAt": "2026-01-13T00:14:53.597Z",
      "spaceId": "V2At0Z7gcRc-uHEuMrYVO",
      "userId": "84tJq5nDb6RSP9qIPqsYs",
      "linkToCardId": null
    },
    {
      "id": "ESZtEWZlx_7AAYVx7B0fR",
      "x": 119,
      "y": 1113,
      "z": 2548,
      "name": "Hi, I'm Piri, and I make Kinopio.\n\nI believe in building software that's economically-sustainable and built-to-last. Kinopio is 100% funded and made possible by people like you.\n\nEmail me anytime at [hi@kinopio.club](mailto:hi@kinopio.club)",
      "frameId": 0,
      "isRemoved": false,
      "nameUpdatedAt": "2026-01-12T22:12:07.126Z",
      "nameUpdatedByUserId": "euGhpBrR9eBcjKnK16C_g",
      "linkToSpaceId": null,
      "linkToCardId": null,
      "linkToSpaceCollaboratorKey": null,
      "urlPreviewIsVisible": true,
      "shouldShowOtherSpacePreviewImage": true,
      "shouldHideUrlPreviewInfo": false,
      "shouldHideUrlPreviewImage": false,
      "shouldUpdateUrlPreview": false,
      "isLocked": false,
      "isComment": false,
      "isTodo": false,
      "urlIsVisible": false,
      "urlPreviewUrl": "https://hi@kinopio.cl",
      "urlPreviewImage": null,
      "urlPreviewFavicon": null,
      "urlPreviewTitle": null,
      "urlPreviewDescription": null,
      "urlPreviewErrorUrl": "https://hi@kinopio.cl",
      "urlPreviewEmbedHtml": null,
      "urlPreviewIframeUrl": null,
      "backgroundColor": null,
      "resizeWidth": 239,
      "isCreatedThroughPublicApi": true,
      "counterIsVisible": false,
      "counterValue": 0,
      "codeBlockLanguage": null,
      "width": 239,
      "height": 231,
      "tilt": 0,
      "maxWidth": 200,
      "headerFontId": 8,
      "headerFontSize": "s",
      "createdAt": "2026-01-12T20:10:55.240Z",
      "updatedAt": "2026-01-12T22:12:08.004Z",
      "spaceId": "V2At0Z7gcRc-uHEuMrYVO",
      "userId": "84tJq5nDb6RSP9qIPqsYs"
    },
    {
      "id": "vy4TzdUwtsks0QRuG8tus",
      "x": 849,
      "y": 188,
      "z": 2536,
      "name": "https://www.youtube.com/watch?v=jfKfPfyJRdk",
      "frameId": 0,
      "isRemoved": false,
      "nameUpdatedAt": "2026-01-12T20:34:16.627Z",
      "nameUpdatedByUserId": "euGhpBrR9eBcjKnK16C_g",
      "linkToSpaceId": null,
      "linkToCardId": null,
      "linkToSpaceCollaboratorKey": null,
      "urlPreviewIsVisible": true,
      "shouldShowOtherSpacePreviewImage": false,
      "shouldHideUrlPreviewInfo": false,
      "shouldHideUrlPreviewImage": false,
      "shouldUpdateUrlPreview": false,
      "isLocked": false,
      "isComment": false,
      "isTodo": false,
      "urlIsVisible": false,
      "urlPreviewUrl": "https://www.youtube.com/watch?v=jfKfPfyJRdk",
      "urlPreviewImage": "https://i.ytimg.com/vi/jfKfPfyJRdk/maxresdefault_live.jpg",
      "urlPreviewFavicon": "https://www.youtube.com/s/desktop/28b0985e/img/favicon_144x144.png",
      "urlPreviewTitle": "lofi hip hop radio 📚 - beats to relax/study to",
      "urlPreviewDescription": "🎼 | Listen on Spotify, Apple music and more\n→  https://fanlink.to/lofigirl-music\n\n🌎 | Lofi Girl on all social media\n→  https://fanlink.to/lofigirl-social\n\n👕 | Lofi Girl merch\n→  https://bit.ly/Iofigirl-shop\n\n🎭 | Create your lofi avatar now\n→  https://lofigirl.com/generator/\n\n…",
      "urlPreviewErrorUrl": null,
      "urlPreviewEmbedHtml": null,
      "urlPreviewIframeUrl": "https://www.youtube.com/embed/jfKfPfyJRdk?rel=0&autoplay=1",
      "backgroundColor": null,
      "resizeWidth": 0,
      "isCreatedThroughPublicApi": true,
      "counterIsVisible": false,
      "counterValue": 0,
      "codeBlockLanguage": null,
      "width": 200,
      "height": 206,
      "tilt": 0,
      "maxWidth": null,
      "headerFontId": 0,
      "headerFontSize": "s",
      "createdAt": "2025-06-26T20:37:10.724Z",
      "updatedAt": "2026-01-12T20:54:35.807Z",
      "spaceId": "V2At0Z7gcRc-uHEuMrYVO",
      "userId": "84tJq5nDb6RSP9qIPqsYs",
      "prevWidth": 200,
      "prevHeight": 206
    },
    {
      "id": "maszDniwP_daeQ0GMeADT",
      "x": 844,
      "y": 554,
      "z": 2532,
      "name": "https://cdn.kinopio.club/sxgcwhE5WoypHFn58JF5u/hand-made-patch.webp",
      "frameId": 0,
      "isRemoved": false,
      "nameUpdatedAt": "2024-01-05T19:05:20.339Z",
      "nameUpdatedByUserId": null,
      "linkToSpaceId": null,
      "linkToCardId": null,
      "linkToSpaceCollaboratorKey": null,
      "urlPreviewIsVisible": true,
      "shouldShowOtherSpacePreviewImage": false,
      "shouldHideUrlPreviewInfo": false,
      "shouldHideUrlPreviewImage": false,
      "shouldUpdateUrlPreview": false,
      "isLocked": false,
      "isComment": false,
      "isTodo": null,
      "urlIsVisible": false,
      "urlPreviewUrl": null,
      "urlPreviewImage": null,
      "urlPreviewFavicon": null,
      "urlPreviewTitle": null,
      "urlPreviewDescription": null,
      "urlPreviewErrorUrl": null,
      "urlPreviewEmbedHtml": null,
      "urlPreviewIframeUrl": null,
      "backgroundColor": null,
      "resizeWidth": 176,
      "isCreatedThroughPublicApi": true,
      "counterIsVisible": false,
      "counterValue": 1,
      "codeBlockLanguage": null,
      "width": 176,
      "height": 176,
      "tilt": 0,
      "maxWidth": null,
      "headerFontId": 0,
      "headerFontSize": "s",
      "createdAt": "2022-07-18T21:47:24.289Z",
      "updatedAt": "2026-01-12T20:46:35.843Z",
      "spaceId": "V2At0Z7gcRc-uHEuMrYVO",
      "userId": "84tJq5nDb6RSP9qIPqsYs"
    },
    {
      "id": "TnFsrZjbImor4CTHBbaP2",
      "x": 547,
      "y": 1123,
      "z": 2516,
      "name": "https://pketh.org/organic-software.html [[blog post]]",
      "frameId": 0,
      "isRemoved": false,
      "nameUpdatedAt": "2026-01-12T20:11:30.847Z",
      "nameUpdatedByUserId": "euGhpBrR9eBcjKnK16C_g",
      "linkToSpaceId": null,
      "linkToCardId": null,
      "linkToSpaceCollaboratorKey": null,
      "urlPreviewIsVisible": true,
      "shouldShowOtherSpacePreviewImage": true,
      "shouldHideUrlPreviewInfo": false,
      "shouldHideUrlPreviewImage": true,
      "shouldUpdateUrlPreview": false,
      "isLocked": false,
      "isComment": false,
      "isTodo": false,
      "urlIsVisible": false,
      "urlPreviewUrl": "https://pketh.org/organic-software.html",
      "urlPreviewImage": "https://us-east-1.linodeobjects.com/kinopio-uploads/qHynJB21jZN0iBafr98Fn/73aZiKZLuZGv5J1Zu5z3o/urlPreviewImage.jpg",
      "urlPreviewFavicon": "https://pketh.org/favicon.ico?v=3",
      "urlPreviewTitle": "In Search of Organic Software",
      "urlPreviewDescription": "So over the last couple weeks, I’ve been talking to VCs and founders who have and haven’t taken VC to learn whether it makes sense for Kinopio. I don’t think it does.",
      "urlPreviewErrorUrl": null,
      "urlPreviewEmbedHtml": null,
      "urlPreviewIframeUrl": null,
      "backgroundColor": null,
      "resizeWidth": null,
      "isCreatedThroughPublicApi": true,
      "counterIsVisible": false,
      "counterValue": 0,
      "codeBlockLanguage": null,
      "width": 200,
      "height": 89,
      "tilt": 0,
      "maxWidth": 200,
      "headerFontId": 8,
      "headerFontSize": "s",
      "createdAt": "2026-01-12T20:11:31.769Z",
      "updatedAt": "2026-01-12T20:34:28.114Z",
      "spaceId": "V2At0Z7gcRc-uHEuMrYVO",
      "userId": "84tJq5nDb6RSP9qIPqsYs"
    },
    {
      "id": "8ujA-vok23g_bD7nOR-MI",
      "x": 388,
      "y": 1262,
      "z": 2514,
      "name": "https://pketh.org/how-kinopio-is-made.html [[blog post]]",
      "frameId": 0,
      "isRemoved": false,
      "nameUpdatedAt": "2026-01-12T20:34:26.435Z",
      "nameUpdatedByUserId": "euGhpBrR9eBcjKnK16C_g",
      "linkToSpaceId": null,
      "linkToCardId": null,
      "linkToSpaceCollaboratorKey": null,
      "urlPreviewIsVisible": true,
      "shouldShowOtherSpacePreviewImage": false,
      "shouldHideUrlPreviewInfo": false,
      "shouldHideUrlPreviewImage": false,
      "shouldUpdateUrlPreview": false,
      "isLocked": false,
      "isComment": false,
      "isTodo": false,
      "urlIsVisible": false,
      "urlPreviewUrl": "https://pketh.org/how-kinopio-is-made.html",
      "urlPreviewImage": "https://pketh.org/images/2020/porco-rosso-engine.jpg",
      "urlPreviewFavicon": "https://pketh.org/favicon.ico?v=3",
      "urlPreviewTitle": "How Kinopio is Made",
      "urlPreviewDescription": "You’ve probably heard, or lived, a story that goes like this…",
      "urlPreviewErrorUrl": null,
      "urlPreviewEmbedHtml": null,
      "urlPreviewIframeUrl": null,
      "backgroundColor": null,
      "resizeWidth": 200,
      "isCreatedThroughPublicApi": true,
      "counterIsVisible": false,
      "counterValue": 0,
      "codeBlockLanguage": null,
      "width": 200,
      "height": 175,
      "tilt": 0,
      "maxWidth": null,
      "headerFontId": 0,
      "headerFontSize": "s",
      "createdAt": "2023-07-15T23:21:33.404Z",
      "updatedAt": "2026-01-12T20:34:27.394Z",
      "spaceId": "V2At0Z7gcRc-uHEuMrYVO",
      "userId": "84tJq5nDb6RSP9qIPqsYs",
      "prevWidth": 200,
      "prevHeight": 175
    },
    {
      "id": "qGd2U7MMODuJHTofQtjNw",
      "x": 98,
      "y": 385,
      "z": 2510,
      "name": "Get your thoughts out and visually connect them together",
      "frameId": 1,
      "isRemoved": false,
      "nameUpdatedAt": "2023-07-15T23:07:56.988Z",
      "nameUpdatedByUserId": null,
      "linkToSpaceId": null,
      "linkToCardId": null,
      "linkToSpaceCollaboratorKey": null,
      "urlPreviewIsVisible": true,
      "shouldShowOtherSpacePreviewImage": false,
      "shouldHideUrlPreviewInfo": false,
      "shouldHideUrlPreviewImage": false,
      "shouldUpdateUrlPreview": false,
      "isLocked": false,
      "isComment": false,
      "isTodo": null,
      "urlIsVisible": false,
      "urlPreviewUrl": null,
      "urlPreviewImage": null,
      "urlPreviewFavicon": null,
      "urlPreviewTitle": null,
      "urlPreviewDescription": null,
      "urlPreviewErrorUrl": null,
      "urlPreviewEmbedHtml": null,
      "urlPreviewIframeUrl": null,
      "backgroundColor": null,
      "resizeWidth": 0,
      "isCreatedThroughPublicApi": true,
      "counterIsVisible": false,
      "counterValue": 1,
      "codeBlockLanguage": null,
      "width": 200,
      "height": 69,
      "tilt": 0,
      "maxWidth": null,
      "headerFontId": 0,
      "headerFontSize": "s",
      "createdAt": "2022-07-18T21:47:23.839Z",
      "updatedAt": "2026-01-12T20:33:49.337Z",
      "spaceId": "V2At0Z7gcRc-uHEuMrYVO",
      "userId": "84tJq5nDb6RSP9qIPqsYs"
    },
    {
      "id": "QsP77v15s2VtUPAgXbIEN",
      "x": 517,
      "y": 668,
      "z": 2506,
      "name": "https://cdn.kinopio.club/R4JoZXWYNEbaZ3pRdKHQj/3.mp4",
      "frameId": 0,
      "isRemoved": false,
      "nameUpdatedAt": "2023-12-25T00:25:30.843Z",
      "nameUpdatedByUserId": null,
      "linkToSpaceId": null,
      "linkToCardId": null,
      "linkToSpaceCollaboratorKey": null,
      "urlPreviewIsVisible": true,
      "shouldShowOtherSpacePreviewImage": false,
      "shouldHideUrlPreviewInfo": false,
      "shouldHideUrlPreviewImage": false,
      "shouldUpdateUrlPreview": false,
      "isLocked": false,
      "isComment": false,
      "isTodo": null,
      "urlIsVisible": false,
      "urlPreviewUrl": null,
      "urlPreviewImage": null,
      "urlPreviewFavicon": null,
      "urlPreviewTitle": null,
      "urlPreviewDescription": null,
      "urlPreviewErrorUrl": null,
      "urlPreviewEmbedHtml": null,
      "urlPreviewIframeUrl": null,
      "backgroundColor": null,
      "resizeWidth": 221,
      "isCreatedThroughPublicApi": true,
      "counterIsVisible": false,
      "counterValue": 0,
      "codeBlockLanguage": null,
      "width": 221,
      "height": 125,
      "tilt": 0,
      "maxWidth": null,
      "headerFontId": 0,
      "headerFontSize": "s",
      "createdAt": "2025-06-26T20:37:10.721Z",
      "updatedAt": "2026-01-12T20:25:28.719Z",
      "spaceId": "V2At0Z7gcRc-uHEuMrYVO",
      "userId": "84tJq5nDb6RSP9qIPqsYs"
    },
    {
      "id": "vuIw865BSkVLR9rbBFgc8",
      "x": 151,
      "y": 520,
      "z": 2508,
      "name": "Add cards by tapping anywhere",
      "frameId": null,
      "isRemoved": false,
      "nameUpdatedAt": "2023-12-25T00:02:56.492Z",
      "nameUpdatedByUserId": null,
      "linkToSpaceId": null,
      "linkToCardId": null,
      "linkToSpaceCollaboratorKey": null,
      "urlPreviewIsVisible": true,
      "shouldShowOtherSpacePreviewImage": false,
      "shouldHideUrlPreviewInfo": false,
      "shouldHideUrlPreviewImage": false,
      "shouldUpdateUrlPreview": false,
      "isLocked": false,
      "isComment": false,
      "isTodo": false,
      "urlIsVisible": false,
      "urlPreviewUrl": null,
      "urlPreviewImage": null,
      "urlPreviewFavicon": null,
      "urlPreviewTitle": null,
      "urlPreviewDescription": null,
      "urlPreviewErrorUrl": null,
      "urlPreviewEmbedHtml": null,
      "urlPreviewIframeUrl": null,
      "backgroundColor": "rgb(252, 239, 166)",
      "resizeWidth": 0,
      "isCreatedThroughPublicApi": true,
      "counterIsVisible": false,
      "counterValue": 1,
      "codeBlockLanguage": null,
      "width": 200,
      "height": 51,
      "tilt": 0,
      "maxWidth": null,
      "headerFontId": 0,
      "headerFontSize": "s",
      "createdAt": "2022-07-18T21:47:23.898Z",
      "updatedAt": "2026-01-12T20:25:23.452Z",
      "spaceId": "V2At0Z7gcRc-uHEuMrYVO",
      "userId": "84tJq5nDb6RSP9qIPqsYs"
    },
    {
      "id": "AM1vWSblnwbq5Noa2kuYL",
      "x": 82,
      "y": 138,
      "z": 2494,
      "name": "# Kinopio\n\n## For building ideas and solving problems\n\n[Help and Tutorials](https://help.kinopio.club)",
      "frameId": 0,
      "isRemoved": false,
      "nameUpdatedAt": "2023-07-15T23:07:56.963Z",
      "nameUpdatedByUserId": null,
      "linkToSpaceId": null,
      "linkToCardId": null,
      "linkToSpaceCollaboratorKey": null,
      "urlPreviewIsVisible": true,
      "shouldShowOtherSpacePreviewImage": false,
      "shouldHideUrlPreviewInfo": false,
      "shouldHideUrlPreviewImage": false,
      "shouldUpdateUrlPreview": false,
      "isLocked": false,
      "isComment": false,
      "isTodo": null,
      "urlIsVisible": false,
      "urlPreviewUrl": null,
      "urlPreviewImage": null,
      "urlPreviewFavicon": null,
      "urlPreviewTitle": null,
      "urlPreviewDescription": null,
      "urlPreviewErrorUrl": null,
      "urlPreviewEmbedHtml": null,
      "urlPreviewIframeUrl": null,
      "backgroundColor": null,
      "resizeWidth": 200,
      "isCreatedThroughPublicApi": true,
      "counterIsVisible": false,
      "counterValue": 1,
      "codeBlockLanguage": null,
      "width": 200,
      "height": 167,
      "tilt": 0,
      "maxWidth": null,
      "headerFontId": 0,
      "headerFontSize": "s",
      "createdAt": "2022-07-18T21:47:23.781Z",
      "updatedAt": "2026-01-12T20:18:48.967Z",
      "spaceId": "V2At0Z7gcRc-uHEuMrYVO",
      "userId": "84tJq5nDb6RSP9qIPqsYs"
    },
    {
      "id": "6pih5AWvTHmE_2U_--x-I",
      "x": 617,
      "y": 836,
      "z": 2482,
      "name": "https://cdn.kinopio.club/JjjQdKPST3WoCvech3OjU/4.mp4",
      "frameId": 0,
      "isRemoved": false,
      "nameUpdatedAt": "2023-07-15T23:14:28.047Z",
      "nameUpdatedByUserId": null,
      "linkToSpaceId": null,
      "linkToCardId": null,
      "linkToSpaceCollaboratorKey": null,
      "urlPreviewIsVisible": true,
      "shouldShowOtherSpacePreviewImage": false,
      "shouldHideUrlPreviewInfo": false,
      "shouldHideUrlPreviewImage": false,
      "shouldUpdateUrlPreview": false,
      "isLocked": false,
      "isComment": false,
      "isTodo": null,
      "urlIsVisible": false,
      "urlPreviewUrl": null,
      "urlPreviewImage": null,
      "urlPreviewFavicon": null,
      "urlPreviewTitle": null,
      "urlPreviewDescription": null,
      "urlPreviewErrorUrl": null,
      "urlPreviewEmbedHtml": null,
      "urlPreviewIframeUrl": null,
      "backgroundColor": null,
      "resizeWidth": 234,
      "isCreatedThroughPublicApi": true,
      "counterIsVisible": false,
      "counterValue": 0,
      "codeBlockLanguage": null,
      "width": 234,
      "height": 133,
      "tilt": 0,
      "maxWidth": null,
      "headerFontId": 0,
      "headerFontSize": "s",
      "createdAt": "2023-07-15T23:13:57.544Z",
      "updatedAt": "2026-01-12T20:15:48.033Z",
      "spaceId": "V2At0Z7gcRc-uHEuMrYVO",
      "userId": "84tJq5nDb6RSP9qIPqsYs"
    },
    {
      "id": "dQcvVifK_x2hfbBFmQxpT",
      "x": 111,
      "y": 810,
      "z": 2464,
      "name": "::systemCommand=apps",
      "frameId": 0,
      "isRemoved": false,
      "nameUpdatedAt": "2023-07-15T23:16:31.369Z",
      "nameUpdatedByUserId": null,
      "linkToSpaceId": null,
      "linkToCardId": null,
      "linkToSpaceCollaboratorKey": null,
      "urlPreviewIsVisible": true,
      "shouldShowOtherSpacePreviewImage": false,
      "shouldHideUrlPreviewInfo": false,
      "shouldHideUrlPreviewImage": false,
      "shouldUpdateUrlPreview": false,
      "isLocked": false,
      "isComment": false,
      "isTodo": false,
      "urlIsVisible": false,
      "urlPreviewUrl": null,
      "urlPreviewImage": null,
      "urlPreviewFavicon": null,
      "urlPreviewTitle": null,
      "urlPreviewDescription": null,
      "urlPreviewErrorUrl": null,
      "urlPreviewEmbedHtml": null,
      "urlPreviewIframeUrl": null,
      "backgroundColor": null,
      "resizeWidth": 190,
      "isCreatedThroughPublicApi": true,
      "counterIsVisible": false,
      "counterValue": 1,
      "codeBlockLanguage": null,
      "width": 190,
      "height": 35,
      "tilt": 0,
      "maxWidth": null,
      "headerFontId": 0,
      "headerFontSize": "s",
      "createdAt": "2022-07-18T21:47:24.376Z",
      "updatedAt": "2026-01-12T20:14:44.962Z",
      "spaceId": "V2At0Z7gcRc-uHEuMrYVO",
      "userId": "84tJq5nDb6RSP9qIPqsYs",
      "listId": "KyYPAy6PoUxvPhvFGnqMC",
      "listPositionIndex": "a3",
      "prevWidth": 190,
      "prevHeight": 35
    },
    {
      "id": "Z2sXtooOtj421Qh8R7sFa",
      "x": 111,
      "y": 767,
      "z": 2464,
      "name": "::systemCommand=explore\n",
      "frameId": 0,
      "isRemoved": false,
      "nameUpdatedAt": "2026-01-12T20:09:07.959Z",
      "nameUpdatedByUserId": "euGhpBrR9eBcjKnK16C_g",
      "linkToSpaceId": null,
      "linkToCardId": null,
      "linkToSpaceCollaboratorKey": null,
      "urlPreviewIsVisible": true,
      "shouldShowOtherSpacePreviewImage": true,
      "shouldHideUrlPreviewInfo": false,
      "shouldHideUrlPreviewImage": false,
      "shouldUpdateUrlPreview": false,
      "isLocked": false,
      "isComment": false,
      "isTodo": false,
      "urlIsVisible": false,
      "urlPreviewUrl": null,
      "urlPreviewImage": null,
      "urlPreviewFavicon": null,
      "urlPreviewTitle": null,
      "urlPreviewDescription": null,
      "urlPreviewErrorUrl": null,
      "urlPreviewEmbedHtml": null,
      "urlPreviewIframeUrl": null,
      "backgroundColor": null,
      "resizeWidth": 190,
      "isCreatedThroughPublicApi": true,
      "counterIsVisible": false,
      "counterValue": 0,
      "codeBlockLanguage": null,
      "width": 190,
      "height": 35,
      "tilt": 0,
      "maxWidth": 200,
      "headerFontId": 8,
      "headerFontSize": "s",
      "createdAt": "2026-01-12T20:09:04.210Z",
      "updatedAt": "2026-01-12T20:14:44.843Z",
      "spaceId": "V2At0Z7gcRc-uHEuMrYVO",
      "userId": "84tJq5nDb6RSP9qIPqsYs",
      "listId": "KyYPAy6PoUxvPhvFGnqMC",
      "listPositionIndex": "a2",
      "prevWidth": 190,
      "prevHeight": 35
    },
    {
      "id": "2ijpIgyHvB_6yFww8DSNf",
      "x": 111,
      "y": 724,
      "z": 2464,
      "name": "::systemCommand=templates",
      "frameId": 0,
      "isRemoved": false,
      "nameUpdatedAt": "2023-12-25T00:04:55.972Z",
      "nameUpdatedByUserId": null,
      "linkToSpaceId": null,
      "linkToCardId": null,
      "linkToSpaceCollaboratorKey": null,
      "urlPreviewIsVisible": true,
      "shouldShowOtherSpacePreviewImage": false,
      "shouldHideUrlPreviewInfo": false,
      "shouldHideUrlPreviewImage": false,
      "shouldUpdateUrlPreview": false,
      "isLocked": false,
      "isComment": false,
      "isTodo": false,
      "urlIsVisible": false,
      "urlPreviewUrl": null,
      "urlPreviewImage": null,
      "urlPreviewFavicon": null,
      "urlPreviewTitle": null,
      "urlPreviewDescription": null,
      "urlPreviewErrorUrl": null,
      "urlPreviewEmbedHtml": null,
      "urlPreviewIframeUrl": null,
      "backgroundColor": null,
      "resizeWidth": 190,
      "isCreatedThroughPublicApi": true,
      "counterIsVisible": false,
      "counterValue": 0,
      "codeBlockLanguage": null,
      "width": 190,
      "height": 35,
      "tilt": 0,
      "maxWidth": null,
      "headerFontId": 0,
      "headerFontSize": "s",
      "createdAt": "2025-06-26T20:37:10.718Z",
      "updatedAt": "2026-01-12T20:14:44.772Z",
      "spaceId": "V2At0Z7gcRc-uHEuMrYVO",
      "userId": "84tJq5nDb6RSP9qIPqsYs",
      "listId": "KyYPAy6PoUxvPhvFGnqMC",
      "listPositionIndex": "a1",
      "prevWidth": 190,
      "prevHeight": 35
    },
    {
      "id": "QJSi_5Iay9mn1WzTAC3JR",
      "x": 111,
      "y": 681,
      "z": 2464,
      "name": "::systemCommand=newSpace",
      "frameId": 0,
      "isRemoved": false,
      "nameUpdatedAt": "2023-12-25T00:04:43.761Z",
      "nameUpdatedByUserId": null,
      "linkToSpaceId": null,
      "linkToCardId": null,
      "linkToSpaceCollaboratorKey": null,
      "urlPreviewIsVisible": true,
      "shouldShowOtherSpacePreviewImage": false,
      "shouldHideUrlPreviewInfo": false,
      "shouldHideUrlPreviewImage": false,
      "shouldUpdateUrlPreview": false,
      "isLocked": false,
      "isComment": false,
      "isTodo": null,
      "urlIsVisible": false,
      "urlPreviewUrl": null,
      "urlPreviewImage": null,
      "urlPreviewFavicon": null,
      "urlPreviewTitle": null,
      "urlPreviewDescription": null,
      "urlPreviewErrorUrl": null,
      "urlPreviewEmbedHtml": null,
      "urlPreviewIframeUrl": null,
      "backgroundColor": null,
      "resizeWidth": 190,
      "isCreatedThroughPublicApi": true,
      "counterIsVisible": false,
      "counterValue": 0,
      "codeBlockLanguage": null,
      "width": 190,
      "height": 35,
      "tilt": 0,
      "maxWidth": null,
      "headerFontId": 0,
      "headerFontSize": "s",
      "createdAt": "2025-06-26T20:37:10.715Z",
      "updatedAt": "2026-01-12T20:14:44.631Z",
      "spaceId": "V2At0Z7gcRc-uHEuMrYVO",
      "userId": "84tJq5nDb6RSP9qIPqsYs",
      "listId": "KyYPAy6PoUxvPhvFGnqMC",
      "listPositionIndex": "a0",
      "prevWidth": 190,
      "prevHeight": 35
    },
    {
      "id": "DYzRMyg035nxSwWsbrQtY",
      "x": 432,
      "y": 505,
      "z": 2464,
      "name": "https://updates.kinopio.club/connecting-cards.mp4",
      "frameId": null,
      "isRemoved": false,
      "nameUpdatedAt": "2023-07-16T22:32:27.225Z",
      "nameUpdatedByUserId": null,
      "linkToSpaceId": null,
      "linkToCardId": null,
      "linkToSpaceCollaboratorKey": null,
      "urlPreviewIsVisible": true,
      "shouldShowOtherSpacePreviewImage": false,
      "shouldHideUrlPreviewInfo": false,
      "shouldHideUrlPreviewImage": false,
      "shouldUpdateUrlPreview": false,
      "isLocked": false,
      "isComment": false,
      "isTodo": null,
      "urlIsVisible": false,
      "urlPreviewUrl": null,
      "urlPreviewImage": null,
      "urlPreviewFavicon": null,
      "urlPreviewTitle": null,
      "urlPreviewDescription": null,
      "urlPreviewErrorUrl": null,
      "urlPreviewEmbedHtml": null,
      "urlPreviewIframeUrl": null,
      "backgroundColor": null,
      "resizeWidth": 220,
      "isCreatedThroughPublicApi": true,
      "counterIsVisible": false,
      "counterValue": 1,
      "codeBlockLanguage": null,
      "width": 220,
      "height": 125,
      "tilt": 0,
      "maxWidth": null,
      "headerFontId": 0,
      "headerFontSize": "s",
      "createdAt": "2022-07-18T21:47:24.015Z",
      "updatedAt": "2026-01-12T20:14:43.855Z",
      "spaceId": "V2At0Z7gcRc-uHEuMrYVO",
      "userId": "84tJq5nDb6RSP9qIPqsYs"
    },
    {
      "id": "MP1Ms1CgTb1yNUfll9csy",
      "x": 346,
      "y": 247,
      "z": 2464,
      "name": "Whiteboarding",
      "frameId": 0,
      "isRemoved": false,
      "nameUpdatedAt": "2023-07-15T23:07:57.221Z",
      "nameUpdatedByUserId": null,
      "linkToSpaceId": null,
      "linkToCardId": null,
      "linkToSpaceCollaboratorKey": null,
      "urlPreviewIsVisible": true,
      "shouldShowOtherSpacePreviewImage": false,
      "shouldHideUrlPreviewInfo": false,
      "shouldHideUrlPreviewImage": false,
      "shouldUpdateUrlPreview": false,
      "isLocked": false,
      "isComment": false,
      "isTodo": null,
      "urlIsVisible": false,
      "urlPreviewUrl": null,
      "urlPreviewImage": null,
      "urlPreviewFavicon": null,
      "urlPreviewTitle": null,
      "urlPreviewDescription": null,
      "urlPreviewErrorUrl": null,
      "urlPreviewEmbedHtml": null,
      "urlPreviewIframeUrl": null,
      "backgroundColor": null,
      "resizeWidth": 0,
      "isCreatedThroughPublicApi": true,
      "counterIsVisible": false,
      "counterValue": 0,
      "codeBlockLanguage": null,
      "width": 136,
      "height": 33,
      "tilt": 0,
      "maxWidth": null,
      "headerFontId": 0,
      "headerFontSize": "s",
      "createdAt": "2023-07-15T23:03:11.818Z",
      "updatedAt": "2026-01-12T20:14:43.617Z",
      "spaceId": "V2At0Z7gcRc-uHEuMrYVO",
      "userId": "84tJq5nDb6RSP9qIPqsYs"
    },
    {
      "id": "hc3YOQpD40L2bdytKTAre",
      "x": 358,
      "y": 202,
      "z": 2464,
      "name": "Moodboards",
      "frameId": 0,
      "isRemoved": false,
      "nameUpdatedAt": "2023-07-15T23:07:57.212Z",
      "nameUpdatedByUserId": null,
      "linkToSpaceId": null,
      "linkToCardId": null,
      "linkToSpaceCollaboratorKey": null,
      "urlPreviewIsVisible": true,
      "shouldShowOtherSpacePreviewImage": false,
      "shouldHideUrlPreviewInfo": false,
      "shouldHideUrlPreviewImage": false,
      "shouldUpdateUrlPreview": false,
      "isLocked": false,
      "isComment": false,
      "isTodo": null,
      "urlIsVisible": false,
      "urlPreviewUrl": null,
      "urlPreviewImage": null,
      "urlPreviewFavicon": null,
      "urlPreviewTitle": null,
      "urlPreviewDescription": null,
      "urlPreviewErrorUrl": null,
      "urlPreviewEmbedHtml": null,
      "urlPreviewIframeUrl": null,
      "backgroundColor": null,
      "resizeWidth": 0,
      "isCreatedThroughPublicApi": true,
      "counterIsVisible": false,
      "counterValue": 0,
      "codeBlockLanguage": null,
      "width": 124,
      "height": 33,
      "tilt": 0,
      "maxWidth": null,
      "headerFontId": 0,
      "headerFontSize": "s",
      "createdAt": "2023-07-15T23:03:09.144Z",
      "updatedAt": "2026-01-12T20:14:43.505Z",
      "spaceId": "V2At0Z7gcRc-uHEuMrYVO",
      "userId": "84tJq5nDb6RSP9qIPqsYs"
    },
    {
      "id": "CJQOZi9m61OgVh-L7fTAO",
      "x": 540,
      "y": 188,
      "z": 2464,
      "name": "Create Lively Freeform Spaces\n\nhttps://updates.kinopio.club/delica-van-small.jpg",
      "frameId": 0,
      "isRemoved": false,
      "nameUpdatedAt": "2023-07-16T22:31:32.712Z",
      "nameUpdatedByUserId": null,
      "linkToSpaceId": null,
      "linkToCardId": null,
      "linkToSpaceCollaboratorKey": null,
      "urlPreviewIsVisible": true,
      "shouldShowOtherSpacePreviewImage": false,
      "shouldHideUrlPreviewInfo": false,
      "shouldHideUrlPreviewImage": false,
      "shouldUpdateUrlPreview": false,
      "isLocked": false,
      "isComment": false,
      "isTodo": null,
      "urlIsVisible": false,
      "urlPreviewUrl": null,
      "urlPreviewImage": null,
      "urlPreviewFavicon": null,
      "urlPreviewTitle": null,
      "urlPreviewDescription": null,
      "urlPreviewErrorUrl": null,
      "urlPreviewEmbedHtml": null,
      "urlPreviewIframeUrl": null,
      "backgroundColor": null,
      "resizeWidth": 259,
      "isCreatedThroughPublicApi": true,
      "counterIsVisible": false,
      "counterValue": 1,
      "codeBlockLanguage": null,
      "width": 259,
      "height": 185,
      "tilt": 0,
      "maxWidth": null,
      "headerFontId": 0,
      "headerFontSize": "s",
      "createdAt": "2022-07-18T21:47:23.956Z",
      "updatedAt": "2026-01-12T20:14:43.358Z",
      "spaceId": "V2At0Z7gcRc-uHEuMrYVO",
      "userId": "84tJq5nDb6RSP9qIPqsYs"
    },
    {
      "id": "Vyf0EfpD5KCoWuJ0BZ5aJ",
      "x": 364,
      "y": 157,
      "z": 2464,
      "name": "Note Taking",
      "frameId": 0,
      "isRemoved": false,
      "nameUpdatedAt": "2023-07-15T23:07:57.199Z",
      "nameUpdatedByUserId": null,
      "linkToSpaceId": null,
      "linkToCardId": null,
      "linkToSpaceCollaboratorKey": null,
      "urlPreviewIsVisible": true,
      "shouldShowOtherSpacePreviewImage": false,
      "shouldHideUrlPreviewInfo": false,
      "shouldHideUrlPreviewImage": false,
      "shouldUpdateUrlPreview": false,
      "isLocked": false,
      "isComment": false,
      "isTodo": null,
      "urlIsVisible": false,
      "urlPreviewUrl": null,
      "urlPreviewImage": null,
      "urlPreviewFavicon": null,
      "urlPreviewTitle": null,
      "urlPreviewDescription": null,
      "urlPreviewErrorUrl": null,
      "urlPreviewEmbedHtml": null,
      "urlPreviewIframeUrl": null,
      "backgroundColor": null,
      "resizeWidth": 0,
      "isCreatedThroughPublicApi": true,
      "counterIsVisible": false,
      "counterValue": 0,
      "codeBlockLanguage": null,
      "width": 118,
      "height": 33,
      "tilt": 0,
      "maxWidth": null,
      "headerFontId": 0,
      "headerFontSize": "s",
      "createdAt": "2023-07-15T23:03:03.803Z",
      "updatedAt": "2026-01-12T20:14:42.948Z",
      "spaceId": "V2At0Z7gcRc-uHEuMrYVO",
      "userId": "84tJq5nDb6RSP9qIPqsYs"
    }
  ],
  "connections": [
    {
      "id": "JS46qRxhDKWpMrjti4eBo",
      "startItemId": "ESZtEWZlx_7AAYVx7B0fR",
      "endItemId": "TnFsrZjbImor4CTHBbaP2",
      "path": "m343,1128 q90,40 389,10",
      "labelIsVisible": false,
      "labelRelativePositionX": 0.5,
      "labelRelativePositionY": 0.5,
      "directionIsVisible": false,
      "controlPoint": null,
      "createdAt": "2026-01-12T20:12:40.528Z",
      "updatedAt": "2026-01-12T22:12:08.019Z",
      "spaceId": "qHynJB21jZN0iBafr98Fn",
      "userId": "84tJq5nDb6RSP9qIPqsYs",
      "connectionTypeId": "hpowyO_6Rh5d1LqQQaGTQ"
    },
    {
      "id": "qKKgPuSa4bsDjsGJ_FNqw",
      "startItemId": "QsP77v15s2VtUPAgXbIEN",
      "endItemId": "6pih5AWvTHmE_2U_--x-I",
      "path": "m723,683 q90,40 113,168",
      "labelIsVisible": false,
      "labelRelativePositionX": 0.5,
      "labelRelativePositionY": 0.5,
      "directionIsVisible": true,
      "controlPoint": null,
      "createdAt": "2026-01-12T20:23:42.113Z",
      "updatedAt": "2026-01-12T20:25:28.749Z",
      "spaceId": "qHynJB21jZN0iBafr98Fn",
      "userId": "84tJq5nDb6RSP9qIPqsYs",
      "connectionTypeId": "WUMcXW5lvlpBqQ5Nh_ucp"
    },
    {
      "id": "FCtq3WyFwqkLJ89OrcSPF",
      "startItemId": "AM1vWSblnwbq5Noa2kuYL",
      "endItemId": "Vyf0EfpD5KCoWuJ0BZ5aJ",
      "path": "m267,153 q90,40 200,19",
      "labelIsVisible": false,
      "labelRelativePositionX": 0.5,
      "labelRelativePositionY": 0.5,
      "directionIsVisible": false,
      "controlPoint": null,
      "createdAt": "2023-07-15T23:03:35.156Z",
      "updatedAt": "2026-01-12T20:18:49.047Z",
      "spaceId": "qHynJB21jZN0iBafr98Fn",
      "userId": "84tJq5nDb6RSP9qIPqsYs",
      "connectionTypeId": "hpowyO_6Rh5d1LqQQaGTQ"
    },
    {
      "id": "I6YEHB51KXqgBwaF7MQfe",
      "startItemId": "AM1vWSblnwbq5Noa2kuYL",
      "endItemId": "hc3YOQpD40L2bdytKTAre",
      "path": "m267,153 q90,40 200,64",
      "labelIsVisible": false,
      "labelRelativePositionX": 0.5,
      "labelRelativePositionY": 0.5,
      "directionIsVisible": false,
      "controlPoint": null,
      "createdAt": "2023-07-15T23:03:39.136Z",
      "updatedAt": "2026-01-12T20:18:49.067Z",
      "spaceId": "qHynJB21jZN0iBafr98Fn",
      "userId": "84tJq5nDb6RSP9qIPqsYs",
      "connectionTypeId": "hpowyO_6Rh5d1LqQQaGTQ"
    },
    {
      "id": "CgKJ0Idd-whPWllK91KUr",
      "startItemId": "AM1vWSblnwbq5Noa2kuYL",
      "endItemId": "MP1Ms1CgTb1yNUfll9csy",
      "path": "m267,153 q90,40 200,109",
      "labelIsVisible": false,
      "labelRelativePositionX": 0.5,
      "labelRelativePositionY": 0.5,
      "directionIsVisible": false,
      "controlPoint": null,
      "createdAt": "2023-07-15T23:03:45.747Z",
      "updatedAt": "2026-01-12T20:18:49.111Z",
      "spaceId": "qHynJB21jZN0iBafr98Fn",
      "userId": "84tJq5nDb6RSP9qIPqsYs",
      "connectionTypeId": "hpowyO_6Rh5d1LqQQaGTQ"
    },
    {
      "id": "JFO9bZYi20DHAwXaeOYt6",
      "startItemId": "qGd2U7MMODuJHTofQtjNw",
      "endItemId": "vuIw865BSkVLR9rbBFgc8",
      "path": "m283,400 q90,40 53,135",
      "labelIsVisible": true,
      "labelRelativePositionX": 0.45112781954887216,
      "labelRelativePositionY": 0.44242424242424244,
      "directionIsVisible": true,
      "controlPoint": null,
      "createdAt": "2022-07-18T21:47:23.421Z",
      "updatedAt": "2026-01-12T20:33:51.094Z",
      "spaceId": "qHynJB21jZN0iBafr98Fn",
      "userId": "84tJq5nDb6RSP9qIPqsYs",
      "connectionTypeId": "WUMcXW5lvlpBqQ5Nh_ucp"
    },
    {
      "id": "Jz2cBLLVGn6nEHNJjA79D",
      "startItemId": "vuIw865BSkVLR9rbBFgc8",
      "endItemId": "DYzRMyg035nxSwWsbrQtY",
      "path": "m336,535 q90,40 301,-15",
      "labelIsVisible": false,
      "labelRelativePositionX": 0.5,
      "labelRelativePositionY": 0.5,
      "directionIsVisible": true,
      "controlPoint": null,
      "createdAt": "2022-07-18T21:47:23.486Z",
      "updatedAt": "2026-01-12T20:25:24.453Z",
      "spaceId": "qHynJB21jZN0iBafr98Fn",
      "userId": "84tJq5nDb6RSP9qIPqsYs",
      "connectionTypeId": "WUMcXW5lvlpBqQ5Nh_ucp"
    },
    {
      "id": "yCp498c7XD64k5SQdsxRH",
      "startItemId": "DYzRMyg035nxSwWsbrQtY",
      "endItemId": "CJQOZi9m61OgVh-L7fTAO",
      "path": "m637,520 q90,40 147,-317",
      "labelIsVisible": false,
      "labelRelativePositionX": 0.5,
      "labelRelativePositionY": 0.5,
      "directionIsVisible": false,
      "controlPoint": null,
      "createdAt": "2022-07-18T21:47:23.531Z",
      "updatedAt": "2026-01-12T20:14:43.456Z",
      "spaceId": "qHynJB21jZN0iBafr98Fn",
      "userId": "84tJq5nDb6RSP9qIPqsYs",
      "connectionTypeId": "WUMcXW5lvlpBqQ5Nh_ucp"
    },
    {
      "id": "pZkZgKf4deA9sZxrvnjnX",
      "startItemId": "ESZtEWZlx_7AAYVx7B0fR",
      "endItemId": "8ujA-vok23g_bD7nOR-MI",
      "path": "m343,1128 q90,40 230,149",
      "labelIsVisible": false,
      "labelRelativePositionX": 0.5,
      "labelRelativePositionY": 0.5,
      "directionIsVisible": false,
      "controlPoint": null,
      "createdAt": "2026-01-12T20:12:41.239Z",
      "updatedAt": "2026-01-12T22:12:08.049Z",
      "spaceId": "qHynJB21jZN0iBafr98Fn",
      "userId": "84tJq5nDb6RSP9qIPqsYs",
      "connectionTypeId": "hpowyO_6Rh5d1LqQQaGTQ"
    },
    {
      "id": "uAZakgzs-3Ie-IDcbm_p7",
      "startItemId": "DYzRMyg035nxSwWsbrQtY",
      "endItemId": "QsP77v15s2VtUPAgXbIEN",
      "path": "m637,520 q90,40 86,163",
      "labelIsVisible": false,
      "labelRelativePositionX": 0.5,
      "labelRelativePositionY": 0.5,
      "directionIsVisible": true,
      "controlPoint": null,
      "createdAt": "2025-06-26T20:37:10.641Z",
      "updatedAt": "2026-01-12T20:25:28.808Z",
      "spaceId": "qHynJB21jZN0iBafr98Fn",
      "userId": "84tJq5nDb6RSP9qIPqsYs",
      "connectionTypeId": "WUMcXW5lvlpBqQ5Nh_ucp"
    }
  ],
  "connectionTypes": [
    {
      "id": "WUMcXW5lvlpBqQ5Nh_ucp",
      "name": "How to Use",
      "color": "rgb(123, 238, 159)",
      "createdAt": "2022-07-18T21:47:23.401Z",
      "updatedAt": "2026-01-12T20:08:11.637Z",
      "spaceId": "qHynJB21jZN0iBafr98Fn",
      "userId": "84tJq5nDb6RSP9qIPqsYs"
    },
    {
      "id": "hpowyO_6Rh5d1LqQQaGTQ",
      "name": "Examples",
      "color": "#ffca99",
      "createdAt": "2022-07-18T21:47:23.409Z",
      "updatedAt": "2026-01-12T20:08:11.676Z",
      "spaceId": "qHynJB21jZN0iBafr98Fn",
      "userId": "84tJq5nDb6RSP9qIPqsYs"
    }
  ],
  "cacheDate": 1768263292927,
  "removedCards": [],
  "originSpaceId": "",
  "tags": [
    {
      "id": "rPH9OvFQwwVDsYWTbGnF5",
      "name": "blog post",
      "color": "#fcb8eb",
      "userId": "84tJq5nDb6RSP9qIPqsYs",
      "createdAt": "2026-01-12T20:11:37.823Z",
      "updatedAt": "2026-01-12T20:13:07.821Z",
      "cardId": "8ujA-vok23g_bD7nOR-MI",
      "spaceId": "V2At0Z7gcRc-uHEuMrYVO"
    },
    {
      "id": "5iYCa3KHhq0J7sb1vXLiR",
      "name": "blog post",
      "color": "#fcb8eb",
      "userId": "84tJq5nDb6RSP9qIPqsYs",
      "createdAt": "2026-01-12T20:11:31.876Z",
      "updatedAt": "2026-01-12T20:13:07.821Z",
      "cardId": "TnFsrZjbImor4CTHBbaP2",
      "spaceId": "V2At0Z7gcRc-uHEuMrYVO"
    },
    {
      "id": "zxOrFtUr3nifxsZY5g--N",
      "name": "blog post",
      "color": "#fcb8eb",
      "userId": "84tJq5nDb6RSP9qIPqsYs",
      "createdAt": "2026-01-12T20:34:28.183Z",
      "updatedAt": "2026-01-12T20:34:28.183Z",
      "cardId": "8ujA-vok23g_bD7nOR-MI",
      "spaceId": "V2At0Z7gcRc-uHEuMrYVO"
    }
  ],
  "boxes": [],
  "lines": [
    {
      "id": "ZrbfrjRovIF2ERrTU891f",
      "name": "Who Makes Kinopio?",
      "y": 1026,
      "color": "rgb(12, 155, 31)",
      "createdAt": "2026-01-12T20:10:25.998Z",
      "updatedAt": "2026-01-12T20:35:25.624Z",
      "spaceId": "qHynJB21jZN0iBafr98Fn",
      "userId": "84tJq5nDb6RSP9qIPqsYs"
    },
    {
      "id": "MxvZVBXxZcJE7ZFjgBvPQ",
      "name": "Some of My Spaces",
      "y": 1517,
      "color": "rgb(12, 155, 31)",
      "createdAt": "2026-01-12T20:34:51.125Z",
      "updatedAt": "2026-01-12T20:35:30.685Z",
      "spaceId": "qHynJB21jZN0iBafr98Fn",
      "userId": "84tJq5nDb6RSP9qIPqsYs"
    }
  ],
  "lists": [
    {
      "id": "KyYPAy6PoUxvPhvFGnqMC",
      "y": 647,
      "x": 103,
      "color": "rgb(12, 155, 31)",
      "resizeWidth": 206,
      "height": 206,
      "isCollapsed": false,
      "name": "Get Started",
      "userId": "84tJq5nDb6RSP9qIPqsYs",
      "spaceId": "V2At0Z7gcRc-uHEuMrYVO",
      "z": 22,
      "frameId": 0
    }
  ],
  "visits": 0,
  "isRemoved": false,
  "groupId": null,
  "group": null,
  "drawingStrokes": [
    [
      {
        "id": "PRP4ash3mAfpIWnNFjo4P",
        "x": 298,
        "y": 702,
        "color": "#a0f7f0",
        "diameter": 20,
        "userId": "84tJq5nDb6RSP9qIPqsYs"
      },
      {
        "id": "MIEMmVoJ8pdcqllL2ZGQg",
        "x": 299,
        "y": 703,
        "color": "#a0f7f0",
        "diameter": 20,
        "userId": "84tJq5nDb6RSP9qIPqsYs"
      },
      {
        "id": "bZAFEcpZsGZaPnZVv45So",
        "x": 299,
        "y": 703,
        "color": "#a0f7f0",
        "diameter": 20,
        "userId": "84tJq5nDb6RSP9qIPqsYs"
      },
      {
        "id": "BGokdGrCtWGI6CTymnQ_C",
        "x": 301,
        "y": 704,
        "color": "#a0f7f0",
        "diameter": 20,
        "userId": "84tJq5nDb6RSP9qIPqsYs"
      },
      {
        "id": "N2dyTTPi-EOAOgBPhL-xI",
        "x": 303,
        "y": 705,
        "color": "#a0f7f0",
        "diameter": 20,
        "userId": "84tJq5nDb6RSP9qIPqsYs"
      },
      {
        "id": "YEoQlGwsaHIKTLB6vTXd4",
        "x": 305,
        "y": 706,
        "color": "#a0f7f0",
        "diameter": 20,
        "userId": "84tJq5nDb6RSP9qIPqsYs"
      },
      {
        "id": "dF9hXnKN3vvLDfSOvIwSi",
        "x": 307,
        "y": 707,
        "color": "#a0f7f0",
        "diameter": 20,
        "userId": "84tJq5nDb6RSP9qIPqsYs"
      },
      {
        "id": "rHUM-w8rMuyLzlwCcWUU2",
        "x": 309,
        "y": 709,
        "color": "#a0f7f0",
        "diameter": 20,
        "userId": "84tJq5nDb6RSP9qIPqsYs"
      },
      {
        "id": "eVPItleykTI93d0OxR9B8",
        "x": 311,
        "y": 710,
        "color": "#a0f7f0",
        "diameter": 20,
        "userId": "84tJq5nDb6RSP9qIPqsYs"
      },
      {
        "id": "5eiU19ye-zu57TABR5b0G",
        "x": 313,
        "y": 711,
        "color": "#a0f7f0",
        "diameter": 20,
        "userId": "84tJq5nDb6RSP9qIPqsYs"
      },
      {
        "id": "mspAuQBgvPzfryKjjfhIk",
        "x": 314,
        "y": 712,
        "color": "#a0f7f0",
        "diameter": 20,
        "userId": "84tJq5nDb6RSP9qIPqsYs"
      },
      {
        "id": "KOYmccU9W10DliiSuzF9l",
        "x": 315,
        "y": 712,
        "color": "#a0f7f0",
        "diameter": 20,
        "userId": "84tJq5nDb6RSP9qIPqsYs"
      },
      {
        "id": "EnSiLP4G0BIvjx0YFdUQT",
        "x": 316,
        "y": 713,
        "color": "#a0f7f0",
        "diameter": 20,
        "userId": "84tJq5nDb6RSP9qIPqsYs"
      },
      {
        "id": "jBnq_Uy6CjzcNickhGS9i",
        "x": 318,
        "y": 713,
        "color": "#a0f7f0",
        "diameter": 20,
        "userId": "84tJq5nDb6RSP9qIPqsYs"
      },
      {
        "id": "-_wv7q7n4ApqZ1NUM-d_v",
        "x": 319,
        "y": 714,
        "color": "#a0f7f0",
        "diameter": 20,
        "userId": "84tJq5nDb6RSP9qIPqsYs"
      },
      {
        "id": "NqWLGzIznBv4_sitFkl_3",
        "x": 321,
        "y": 715,
        "color": "#a0f7f0",
        "diameter": 20,
        "userId": "84tJq5nDb6RSP9qIPqsYs"
      },
      {
        "id": "SD1Dm4N2GplqomMQwLoX5",
        "x": 322,
        "y": 716,
        "color": "#a0f7f0",
        "diameter": 20,
        "userId": "84tJq5nDb6RSP9qIPqsYs"
      },
      {
        "id": "5KLIE-elhNnUhL4_Sx1x6",
        "x": 324,
        "y": 717,
        "color": "#a0f7f0",
        "diameter": 20,
        "userId": "84tJq5nDb6RSP9qIPqsYs"
      },
      {
        "id": "hvmApVh4LR4d1YIEMlQSm",
        "x": 324,
        "y": 717,
        "color": "#a0f7f0",
        "diameter": 20,
        "userId": "84tJq5nDb6RSP9qIPqsYs"
      },
      {
        "id": "diR2Do8SHtI5SoRBU68sv",
        "x": 325,
        "y": 717,
        "color": "#a0f7f0",
        "diameter": 20,
        "userId": "84tJq5nDb6RSP9qIPqsYs"
      },
      {
        "id": "qkO9Ys4gH2Hn3i2JrbNth",
        "x": 326,
        "y": 718,
        "color": "#a0f7f0",
        "diameter": 20,
        "userId": "84tJq5nDb6RSP9qIPqsYs"
      },
      {
        "id": "z-Bqngr3r9WyHnEuSqq28",
        "x": 327,
        "y": 719,
        "color": "#a0f7f0",
        "diameter": 20,
        "userId": "84tJq5nDb6RSP9qIPqsYs"
      },
      {
        "id": "vQz8siDikbyoTHJXcoSPd",
        "x": 329,
        "y": 719,
        "color": "#a0f7f0",
        "diameter": 20,
        "userId": "84tJq5nDb6RSP9qIPqsYs"
      },
      {
        "id": "bOE4VetYo9TT6Ur1Hk_6H",
        "x": 329,
        "y": 719,
        "color": "#a0f7f0",
        "diameter": 20,
        "userId": "84tJq5nDb6RSP9qIPqsYs"
      }
    ],
    [
      {
        "id": "ZEWPmCqgQI6DSCQuhvF_L",
        "x": 315,
        "y": 673,
        "color": "#a0f7f0",
        "diameter": 20,
        "userId": "84tJq5nDb6RSP9qIPqsYs"
      },
      {
        "id": "e6tQ28xU9fXz9nAjqg3tl",
        "x": 315,
        "y": 674,
        "color": "#a0f7f0",
        "diameter": 20,
        "userId": "84tJq5nDb6RSP9qIPqsYs"
      },
      {
        "id": "fmwThjfDuT4EjAwATI2G3",
        "x": 315,
        "y": 676,
        "color": "#a0f7f0",
        "diameter": 20,
        "userId": "84tJq5nDb6RSP9qIPqsYs"
      },
      {
        "id": "ONyzKjSONtgA1M-xSXMmg",
        "x": 314,
        "y": 677,
        "color": "#a0f7f0",
        "diameter": 20,
        "userId": "84tJq5nDb6RSP9qIPqsYs"
      },
      {
        "id": "56EJ5yGFFOshxr3_q3HEV",
        "x": 312,
        "y": 679,
        "color": "#a0f7f0",
        "diameter": 20,
        "userId": "84tJq5nDb6RSP9qIPqsYs"
      },
      {
        "id": "kiXc-8KRwfqiH6uk59qp3",
        "x": 312,
        "y": 681,
        "color": "#a0f7f0",
        "diameter": 20,
        "userId": "84tJq5nDb6RSP9qIPqsYs"
      },
      {
        "id": "MktiO2mI07NHgGXn7ljG7",
        "x": 311,
        "y": 682,
        "color": "#a0f7f0",
        "diameter": 20,
        "userId": "84tJq5nDb6RSP9qIPqsYs"
      },
      {
        "id": "oCTXXzlLGVt2UaAQ33HBy",
        "x": 310,
        "y": 684,
        "color": "#a0f7f0",
        "diameter": 20,
        "userId": "84tJq5nDb6RSP9qIPqsYs"
      },
      {
        "id": "4Wh0y_SdrT6q3ERsJw2tB",
        "x": 308,
        "y": 686,
        "color": "#a0f7f0",
        "diameter": 20,
        "userId": "84tJq5nDb6RSP9qIPqsYs"
      },
      {
        "id": "oRIXJd-zoocu2ODWhwj2q",
        "x": 308,
        "y": 687,
        "color": "#a0f7f0",
        "diameter": 20,
        "userId": "84tJq5nDb6RSP9qIPqsYs"
      },
      {
        "id": "7ilonnr5FVJNOWo4dX-qd",
        "x": 306,
        "y": 688,
        "color": "#a0f7f0",
        "diameter": 20,
        "userId": "84tJq5nDb6RSP9qIPqsYs"
      },
      {
        "id": "9f42dvlXm-houeRIOw1g_",
        "x": 305,
        "y": 689,
        "color": "#a0f7f0",
        "diameter": 20,
        "userId": "84tJq5nDb6RSP9qIPqsYs"
      },
      {
        "id": "-OQgomxN4CIhGlajPWIFp",
        "x": 305,
        "y": 690,
        "color": "#a0f7f0",
        "diameter": 20,
        "userId": "84tJq5nDb6RSP9qIPqsYs"
      },
      {
        "id": "mMVVmQGFJRjCcXUGOV303",
        "x": 304,
        "y": 691,
        "color": "#a0f7f0",
        "diameter": 20,
        "userId": "84tJq5nDb6RSP9qIPqsYs"
      },
      {
        "id": "HVyG4QDUDRzf54L-UDI92",
        "x": 303,
        "y": 691,
        "color": "#a0f7f0",
        "diameter": 20,
        "userId": "84tJq5nDb6RSP9qIPqsYs"
      },
      {
        "id": "7KhwuA749YOPo7T80QRAq",
        "x": 302,
        "y": 692,
        "color": "#a0f7f0",
        "diameter": 20,
        "userId": "84tJq5nDb6RSP9qIPqsYs"
      },
      {
        "id": "r3DgxysNRRbrU5ckmht6t",
        "x": 301,
        "y": 693,
        "color": "#a0f7f0",
        "diameter": 20,
        "userId": "84tJq5nDb6RSP9qIPqsYs"
      },
      {
        "id": "xo4xge8TTRjANEyWhord0",
        "x": 300,
        "y": 694,
        "color": "#a0f7f0",
        "diameter": 20,
        "userId": "84tJq5nDb6RSP9qIPqsYs"
      },
      {
        "id": "yM4k5GmZwxydqdb6urf4P",
        "x": 299,
        "y": 695,
        "color": "#a0f7f0",
        "diameter": 20,
        "userId": "84tJq5nDb6RSP9qIPqsYs"
      },
      {
        "id": "AOxqVHJEOwQWQKPdJjL2U",
        "x": 298,
        "y": 696,
        "color": "#a0f7f0",
        "diameter": 20,
        "userId": "84tJq5nDb6RSP9qIPqsYs"
      },
      {
        "id": "c6zpbgIYBm4MBkz9Zl-JM",
        "x": 298,
        "y": 697,
        "color": "#a0f7f0",
        "diameter": 20,
        "userId": "84tJq5nDb6RSP9qIPqsYs"
      },
      {
        "id": "kX_e1DO_5m4pCqVuZLTLB",
        "x": 297,
        "y": 697,
        "color": "#a0f7f0",
        "diameter": 20,
        "userId": "84tJq5nDb6RSP9qIPqsYs"
      },
      {
        "id": "4-fhyVyZXgPPQH3kXqp0K",
        "x": 297,
        "y": 697,
        "color": "#a0f7f0",
        "diameter": 20,
        "userId": "84tJq5nDb6RSP9qIPqsYs"
      },
      {
        "id": "jjqSMKVnsItuxKpRm2VeD",
        "x": 297,
        "y": 698,
        "color": "#a0f7f0",
        "diameter": 20,
        "userId": "84tJq5nDb6RSP9qIPqsYs"
      },
      {
        "id": "xH30X8m-QxLBVV08igp7W",
        "x": 297,
        "y": 698,
        "color": "#a0f7f0",
        "diameter": 20,
        "userId": "84tJq5nDb6RSP9qIPqsYs"
      },
      {
        "id": "hbFA5d6NSGVFWm5bkEX4I",
        "x": 296,
        "y": 698,
        "color": "#a0f7f0",
        "diameter": 20,
        "userId": "84tJq5nDb6RSP9qIPqsYs"
      },
      {
        "id": "GPS5Pj-zG-_our2OPLGJi",
        "x": 296,
        "y": 699,
        "color": "#a0f7f0",
        "diameter": 20,
        "userId": "84tJq5nDb6RSP9qIPqsYs"
      },
      {
        "id": "3DMq90t7QtYIDcRAkFU4d",
        "x": 296,
        "y": 699,
        "color": "#a0f7f0",
        "diameter": 20,
        "userId": "84tJq5nDb6RSP9qIPqsYs"
      },
      {
        "id": "C1Q-bBZuONAx8hOpbO4zN",
        "x": 296,
        "y": 700,
        "color": "#a0f7f0",
        "diameter": 20,
        "userId": "84tJq5nDb6RSP9qIPqsYs"
      }
    ],
    [
      {
        "id": "D5q6-qIGhQg06zcyPj8Sx",
        "x": 392,
        "y": 653,
        "color": "#a0f7f0",
        "diameter": 20,
        "userId": "84tJq5nDb6RSP9qIPqsYs"
      },
      {
        "id": "qq2_iFsjlJlN7BArJGuJY",
        "x": 391,
        "y": 655,
        "color": "#a0f7f0",
        "diameter": 20,
        "userId": "84tJq5nDb6RSP9qIPqsYs"
      },
      {
        "id": "ZQqL4EWxRGe4lHVox8QVJ",
        "x": 390,
        "y": 657,
        "color": "#a0f7f0",
        "diameter": 20,
        "userId": "84tJq5nDb6RSP9qIPqsYs"
      },
      {
        "id": "V-cA7c4PzUkl9ZyButEJe",
        "x": 388,
        "y": 659,
        "color": "#a0f7f0",
        "diameter": 20,
        "userId": "84tJq5nDb6RSP9qIPqsYs"
      },
      {
        "id": "2EcpNApIZHyvk_YZBTWQN",
        "x": 387,
        "y": 661,
        "color": "#a0f7f0",
        "diameter": 20,
        "userId": "84tJq5nDb6RSP9qIPqsYs"
      },
      {
        "id": "bI9QdsFZOt22sK9c4Tqxl",
        "x": 386,
        "y": 663,
        "color": "#a0f7f0",
        "diameter": 20,
        "userId": "84tJq5nDb6RSP9qIPqsYs"
      },
      {
        "id": "5XqFMp-1GEJiIj6ND7Bt3",
        "x": 385,
        "y": 664,
        "color": "#a0f7f0",
        "diameter": 20,
        "userId": "84tJq5nDb6RSP9qIPqsYs"
      },
      {
        "id": "hgiwQCErR_wnQLcMTZtmj",
        "x": 384,
        "y": 666,
        "color": "#a0f7f0",
        "diameter": 20,
        "userId": "84tJq5nDb6RSP9qIPqsYs"
      },
      {
        "id": "uP3yKrByGufnDuJKpNLmg",
        "x": 382,
        "y": 668,
        "color": "#a0f7f0",
        "diameter": 20,
        "userId": "84tJq5nDb6RSP9qIPqsYs"
      },
      {
        "id": "6iW30mN2mOINRc387tacf",
        "x": 381,
        "y": 669,
        "color": "#a0f7f0",
        "diameter": 20,
        "userId": "84tJq5nDb6RSP9qIPqsYs"
      },
      {
        "id": "tnYFAQ0ich3LD5z8ic2PO",
        "x": 380,
        "y": 671,
        "color": "#a0f7f0",
        "diameter": 20,
        "userId": "84tJq5nDb6RSP9qIPqsYs"
      },
      {
        "id": "S-7ADesJD48V35WYyxdRk",
        "x": 379,
        "y": 673,
        "color": "#a0f7f0",
        "diameter": 20,
        "userId": "84tJq5nDb6RSP9qIPqsYs"
      },
      {
        "id": "1Vn7RD78zPcyqAcIFcdCE",
        "x": 377,
        "y": 673,
        "color": "#a0f7f0",
        "diameter": 20,
        "userId": "84tJq5nDb6RSP9qIPqsYs"
      },
      {
        "id": "moNFchfTw0Z5jikZhX1Rh",
        "x": 376,
        "y": 675,
        "color": "#a0f7f0",
        "diameter": 20,
        "userId": "84tJq5nDb6RSP9qIPqsYs"
      },
      {
        "id": "8-9GIaprMEFiRa39X-9RN",
        "x": 374,
        "y": 677,
        "color": "#a0f7f0",
        "diameter": 20,
        "userId": "84tJq5nDb6RSP9qIPqsYs"
      },
      {
        "id": "ksXA0aMR8OImppeHy-h8M",
        "x": 372,
        "y": 679,
        "color": "#a0f7f0",
        "diameter": 20,
        "userId": "84tJq5nDb6RSP9qIPqsYs"
      },
      {
        "id": "SjgQBcoBT_lV4Xhc_tSBz",
        "x": 370,
        "y": 680,
        "color": "#a0f7f0",
        "diameter": 20,
        "userId": "84tJq5nDb6RSP9qIPqsYs"
      },
      {
        "id": "EK5BzB4s5rs5Z3olbTBTe",
        "x": 368,
        "y": 681,
        "color": "#a0f7f0",
        "diameter": 20,
        "userId": "84tJq5nDb6RSP9qIPqsYs"
      },
      {
        "id": "ZPSc4yR5OQ3Ppac6Bmhd-",
        "x": 366,
        "y": 683,
        "color": "#a0f7f0",
        "diameter": 20,
        "userId": "84tJq5nDb6RSP9qIPqsYs"
      },
      {
        "id": "L-QYvWnnd_0Gh9Lszaaz-",
        "x": 364,
        "y": 684,
        "color": "#a0f7f0",
        "diameter": 20,
        "userId": "84tJq5nDb6RSP9qIPqsYs"
      },
      {
        "id": "Dm6f82DtJT-Ne5x99rAdO",
        "x": 363,
        "y": 685,
        "color": "#a0f7f0",
        "diameter": 20,
        "userId": "84tJq5nDb6RSP9qIPqsYs"
      },
      {
        "id": "0XQXT66sTZzsWhRS-BR7v",
        "x": 362,
        "y": 685,
        "color": "#a0f7f0",
        "diameter": 20,
        "userId": "84tJq5nDb6RSP9qIPqsYs"
      },
      {
        "id": "kptW7HO0yWfmPnG4zANif",
        "x": 360,
        "y": 686,
        "color": "#a0f7f0",
        "diameter": 20,
        "userId": "84tJq5nDb6RSP9qIPqsYs"
      },
      {
        "id": "qnZTA2f8BOnj-vOsmGf0E",
        "x": 358,
        "y": 687,
        "color": "#a0f7f0",
        "diameter": 20,
        "userId": "84tJq5nDb6RSP9qIPqsYs"
      },
      {
        "id": "6T_hSnvbCGH8rh03W3MeI",
        "x": 356,
        "y": 688,
        "color": "#a0f7f0",
        "diameter": 20,
        "userId": "84tJq5nDb6RSP9qIPqsYs"
      },
      {
        "id": "kKH7KpepYh_UMkjeRhOtG",
        "x": 353,
        "y": 688,
        "color": "#a0f7f0",
        "diameter": 20,
        "userId": "84tJq5nDb6RSP9qIPqsYs"
      },
      {
        "id": "TNvhaQL2ZmhgqUm_LnvZP",
        "x": 351,
        "y": 689,
        "color": "#a0f7f0",
        "diameter": 20,
        "userId": "84tJq5nDb6RSP9qIPqsYs"
      },
      {
        "id": "Um3QkHeN8MrBjLdwsuOU1",
        "x": 347,
        "y": 690,
        "color": "#a0f7f0",
        "diameter": 20,
        "userId": "84tJq5nDb6RSP9qIPqsYs"
      },
      {
        "id": "9LalPAiJr-vTZGEdbPiWP",
        "x": 343,
        "y": 691,
        "color": "#a0f7f0",
        "diameter": 20,
        "userId": "84tJq5nDb6RSP9qIPqsYs"
      },
      {
        "id": "XPZNf3OcQlQDVoJiV47Yz",
        "x": 340,
        "y": 692,
        "color": "#a0f7f0",
        "diameter": 20,
        "userId": "84tJq5nDb6RSP9qIPqsYs"
      },
      {
        "id": "xvYqtL4W9ITIk1yl1xEpt",
        "x": 337,
        "y": 692,
        "color": "#a0f7f0",
        "diameter": 20,
        "userId": "84tJq5nDb6RSP9qIPqsYs"
      },
      {
        "id": "KkmL85g9lRsEPFTpNM5LO",
        "x": 334,
        "y": 692,
        "color": "#a0f7f0",
        "diameter": 20,
        "userId": "84tJq5nDb6RSP9qIPqsYs"
      },
      {
        "id": "t77MQqmAK8X2DpKQiVLl_",
        "x": 332,
        "y": 693,
        "color": "#a0f7f0",
        "diameter": 20,
        "userId": "84tJq5nDb6RSP9qIPqsYs"
      },
      {
        "id": "JvFsmbtw5_UyDKpT1yFkW",
        "x": 330,
        "y": 694,
        "color": "#a0f7f0",
        "diameter": 20,
        "userId": "84tJq5nDb6RSP9qIPqsYs"
      },
      {
        "id": "1s0S3fbdu7L4N2gpY_Uip",
        "x": 328,
        "y": 694,
        "color": "#a0f7f0",
        "diameter": 20,
        "userId": "84tJq5nDb6RSP9qIPqsYs"
      },
      {
        "id": "IVDQkpbNs2zaf25NJnpN1",
        "x": 326,
        "y": 694,
        "color": "#a0f7f0",
        "diameter": 20,
        "userId": "84tJq5nDb6RSP9qIPqsYs"
      },
      {
        "id": "uMlD9xUPFBBqvzE_qd2y6",
        "x": 323,
        "y": 695,
        "color": "#a0f7f0",
        "diameter": 20,
        "userId": "84tJq5nDb6RSP9qIPqsYs"
      },
      {
        "id": "j5tyJ6xn1uZFuwr47gS0Y",
        "x": 322,
        "y": 696,
        "color": "#a0f7f0",
        "diameter": 20,
        "userId": "84tJq5nDb6RSP9qIPqsYs"
      },
      {
        "id": "_XOwLcjgziPiCVFVsRiwx",
        "x": 320,
        "y": 696,
        "color": "#a0f7f0",
        "diameter": 20,
        "userId": "84tJq5nDb6RSP9qIPqsYs"
      },
      {
        "id": "aehU3APg0ZK4RbQUkjMQO",
        "x": 318,
        "y": 696,
        "color": "#a0f7f0",
        "diameter": 20,
        "userId": "84tJq5nDb6RSP9qIPqsYs"
      },
      {
        "id": "O3AKjeJ_SswOHaG51_p1d",
        "x": 317,
        "y": 696,
        "color": "#a0f7f0",
        "diameter": 20,
        "userId": "84tJq5nDb6RSP9qIPqsYs"
      },
      {
        "id": "NbIvDWqCjQDysloXwnqBo",
        "x": 315,
        "y": 697,
        "color": "#a0f7f0",
        "diameter": 20,
        "userId": "84tJq5nDb6RSP9qIPqsYs"
      },
      {
        "id": "lXjNkvRWMB6JkrEjEwICW",
        "x": 314,
        "y": 697,
        "color": "#a0f7f0",
        "diameter": 20,
        "userId": "84tJq5nDb6RSP9qIPqsYs"
      },
      {
        "id": "8GoqLHL6R517DxApiMSyy",
        "x": 313,
        "y": 697,
        "color": "#a0f7f0",
        "diameter": 20,
        "userId": "84tJq5nDb6RSP9qIPqsYs"
      },
      {
        "id": "fw3L2c2GevlehjT-7xj1E",
        "x": 313,
        "y": 698,
        "color": "#a0f7f0",
        "diameter": 20,
        "userId": "84tJq5nDb6RSP9qIPqsYs"
      },
      {
        "id": "WyqFdXrad9xFYrqAstHfA",
        "x": 312,
        "y": 698,
        "color": "#a0f7f0",
        "diameter": 20,
        "userId": "84tJq5nDb6RSP9qIPqsYs"
      },
      {
        "id": "siakn2lXKONhslzI6c7js",
        "x": 312,
        "y": 698,
        "color": "#a0f7f0",
        "diameter": 20,
        "userId": "84tJq5nDb6RSP9qIPqsYs"
      },
      {
        "id": "XI10QL-qojXn7fEeMdPLb",
        "x": 311,
        "y": 698,
        "color": "#a0f7f0",
        "diameter": 20,
        "userId": "84tJq5nDb6RSP9qIPqsYs"
      },
      {
        "id": "d6pyl-aa265_5agCdROf4",
        "x": 311,
        "y": 698,
        "color": "#a0f7f0",
        "diameter": 20,
        "userId": "84tJq5nDb6RSP9qIPqsYs"
      },
      {
        "id": "T33VMk7oubjrLqDseLrR5",
        "x": 311,
        "y": 698,
        "color": "#a0f7f0",
        "diameter": 20,
        "userId": "84tJq5nDb6RSP9qIPqsYs"
      },
      {
        "id": "ptjgFP7iGfT3XqL9Yr_iE",
        "x": 310,
        "y": 698,
        "color": "#a0f7f0",
        "diameter": 20,
        "userId": "84tJq5nDb6RSP9qIPqsYs"
      },
      {
        "id": "Cz1a_lVDmsZDw4Oqe-yMj",
        "x": 310,
        "y": 698,
        "color": "#a0f7f0",
        "diameter": 20,
        "userId": "84tJq5nDb6RSP9qIPqsYs"
      },
      {
        "id": "iJ8YJbsC-u-d1msnF246W",
        "x": 309,
        "y": 698,
        "color": "#a0f7f0",
        "diameter": 20,
        "userId": "84tJq5nDb6RSP9qIPqsYs"
      },
      {
        "id": "qjFZp87m_n49UYpbq3H2K",
        "x": 308,
        "y": 698,
        "color": "#a0f7f0",
        "diameter": 20,
        "userId": "84tJq5nDb6RSP9qIPqsYs"
      },
      {
        "id": "O_vViss1P_E24ryDRe4w4",
        "x": 307,
        "y": 698,
        "color": "#a0f7f0",
        "diameter": 20,
        "userId": "84tJq5nDb6RSP9qIPqsYs"
      },
      {
        "id": "fqal8auOLnXfUPvBW3neQ",
        "x": 306,
        "y": 698,
        "color": "#a0f7f0",
        "diameter": 20,
        "userId": "84tJq5nDb6RSP9qIPqsYs"
      },
      {
        "id": "lmP6RIK5g2-ay195u9CFT",
        "x": 305,
        "y": 697,
        "color": "#a0f7f0",
        "diameter": 20,
        "userId": "84tJq5nDb6RSP9qIPqsYs"
      },
      {
        "id": "5dO3rmv8h8CX9Zm2TwIJn",
        "x": 305,
        "y": 697,
        "color": "#a0f7f0",
        "diameter": 20,
        "userId": "84tJq5nDb6RSP9qIPqsYs"
      }
    ]
  ],
  "drawingImage": "https://cdn.kinopio.club/qHynJB21jZN0iBafr98Fn/drawing.png",
  "userId": "84tJq5nDb6RSP9qIPqsYs",
  "proposedShowInExplore": false,
  "showInExploreUpdatedAt": null,
  "removedByUserId": null,
  "readOnlyKey": "1TmiPozrGvVVoD8I82iA9",
  "previewImage": "https://us-east-1.linodeobjects.com/kinopio-uploads/qHynJB21jZN0iBafr98Fn/preview-image-qHynJB21jZN0iBafr98Fn.png",
  "previewThumbnailImage": "https://us-east-1.linodeobjects.com/kinopio-uploads/qHynJB21jZN0iBafr98Fn/preview-image-thumbnail-qHynJB21jZN0iBafr98Fn.png",
  "isRestrictedByModerator": false,
  "addedToGroupByUserId": null
}