{
  "id": "8B5r-G24hHzRdy9ca4x3-",
  "name": "Hello Kinopio",
  "privacy": "private",
  "showInExplore": false,
  "collaboratorKey": "",
  "users": [],
  "collaborators": [],
  "spectators": [],
  "clients": [],
  "background": "",
  "moonPhase": "",
  "cards": [
    {
      "id": "_yapYwyLozfZcpeefBv8h",
      "x": 59,
      "y": 101,
      "z": 1566,
      "name": "# Kinopio\n\n## Spatial Thinking for New Ideas and Hard Problems\n\n[About Kinopio](https://help.kinopio.club/about)",
      "frameId": 0,
      "userId": "euGhpBrR9eBcjKnK16C_g",
      "urlPreviewIsVisible": true,
      "commentIsVisible": true,
      "width": 235,
      "height": 153,
      "spaceId": "8B5r-G24hHzRdy9ca4x3-",
      "distanceFromOrigin": 117
    },
    {
      "id": "vHmOyLdtdZYYhP6fDSw9q",
      "x": 106,
      "y": 286,
      "z": 1412,
      "name": "Get your thoughts out and visually connect them together",
      "frameId": 1,
      "isRemoved": false,
      "linkToSpaceId": null,
      "commentIsVisible": false,
      "width": 235,
      "height": 63,
      "spaceId": "8B5r-G24hHzRdy9ca4x3-",
      "userId": "euGhpBrR9eBcjKnK16C_g",
      "distanceFromOrigin": 305
    },
    {
      "id": "CJJjlflWfieRV5GzpE9bW",
      "x": 141,
      "y": 398,
      "z": 1445,
      "name": "[] Create new cards  by tapping empty areas",
      "frameId": null,
      "isRemoved": false,
      "linkToSpaceId": null,
      "commentIsVisible": false,
      "width": 235,
      "height": 47,
      "spaceId": "8B5r-G24hHzRdy9ca4x3-",
      "userId": "euGhpBrR9eBcjKnK16C_g",
      "distanceFromOrigin": 422
    },
    {
      "id": "CnODP7HgI_eeczBxGCaub",
      "x": 473,
      "y": 102,
      "z": 1590,
      "name": "Create Lively Freeform Spaces\n\nhttps://kinopio-updates.us-east-1.linodeobjects.com/delica-van-small.jpg",
      "frameId": 0,
      "isRemoved": false,
      "linkToSpaceId": null,
      "commentIsVisible": false,
      "width": 253,
      "height": 182,
      "spaceId": "8B5r-G24hHzRdy9ca4x3-",
      "userId": "euGhpBrR9eBcjKnK16C_g",
      "distanceFromOrigin": 484,
      "resizeWidth": 253
    },
    {
      "id": "eduWHR0rqzT7KNZoxEq7A",
      "x": 141,
      "y": 471,
      "z": 1444,
      "name": "https://us-east-1.linodeobjects.com/kinopio-uploads/c70QiLI9RTDbtOViV2R5Y/tutorial-connection.mp4\n\n",
      "frameId": null,
      "isRemoved": false,
      "linkToSpaceId": null,
      "commentIsVisible": false,
      "width": 235,
      "height": 135,
      "spaceId": "8B5r-G24hHzRdy9ca4x3-",
      "userId": "euGhpBrR9eBcjKnK16C_g",
      "distanceFromOrigin": 492,
      "resizeWidth": null
    },
    {
      "id": "uVMbWMqcXxXubI38hfurw",
      "x": 94,
      "y": 667,
      "z": 1520,
      "name": "`↙ Explore` community spaces, templates\n\nhttps://kinopio-updates.us-east-1.linodeobjects.com/explore.jpeg",
      "frameId": null,
      "isRemoved": false,
      "linkToSpaceId": null,
      "commentIsVisible": false,
      "width": 254,
      "height": 143,
      "spaceId": "8B5r-G24hHzRdy9ca4x3-",
      "userId": "euGhpBrR9eBcjKnK16C_g",
      "distanceFromOrigin": 674,
      "resizeWidth": 254
    },
    {
      "id": "_QI-_MDbK7oZzxcbFUb3d",
      "x": 591,
      "y": 482,
      "z": 1476,
      "name": "More Features\nhttps://kinopio-updates.us-east-1.linodeobjects.com/race-car.png",
      "frameId": 0,
      "isRemoved": false,
      "linkToSpaceId": null,
      "commentIsVisible": true,
      "width": 235,
      "height": 157,
      "spaceId": "8B5r-G24hHzRdy9ca4x3-",
      "userId": "euGhpBrR9eBcjKnK16C_g",
      "distanceFromOrigin": 763
    },
    {
      "id": "BXy5f5rFWdgVS8YOdbvDO",
      "x": 241,
      "y": 829,
      "z": 1522,
      "name": "https://kinopio.club/mind-map-u2Zc1bR0q7bRb16-K5o6X",
      "frameId": null,
      "isRemoved": false,
      "linkToSpaceId": null,
      "commentIsVisible": false,
      "width": 235,
      "height": 63,
      "spaceId": "8B5r-G24hHzRdy9ca4x3-",
      "userId": "euGhpBrR9eBcjKnK16C_g",
      "distanceFromOrigin": 863
    },
    {
      "id": "r2m6p5rYy_wlF3Ao8yQK5",
      "x": 869,
      "y": 101,
      "z": 1395,
      "name": "[[Pricing]] Kinopio is free for 100 cards, afterwards it's $5/month\n\nhttps://us-east-1.linodeobjects.com/kinopio-uploads/ULVF2EpZiImBb_pG4-Jgk/Wii-Shop-Bling.mp3\n",
      "frameId": null,
      "isRemoved": false,
      "linkToSpaceId": null,
      "commentIsVisible": false,
      "width": 235,
      "height": 112,
      "spaceId": "8B5r-G24hHzRdy9ca4x3-",
      "userId": "euGhpBrR9eBcjKnK16C_g",
      "distanceFromOrigin": 875
    },
    {
      "id": "dxXlCQ0nVrJWF-wm31dht",
      "x": 297,
      "y": 874,
      "z": 1521,
      "name": "https://kinopio.club/meeting-b87U9WETGvl17BrKNsqDH",
      "frameId": null,
      "isRemoved": false,
      "linkToSpaceId": null,
      "commentIsVisible": false,
      "width": 235,
      "height": 63,
      "spaceId": "8B5r-G24hHzRdy9ca4x3-",
      "userId": "euGhpBrR9eBcjKnK16C_g",
      "distanceFromOrigin": 923
    },
    {
      "id": "JSXhmb1Fc-9Fau-qq7h32",
      "x": 694,
      "y": 655,
      "z": 1572,
      "name": "Use [[Tags]] to organize related cards across spaces",
      "frameId": 0,
      "userId": "euGhpBrR9eBcjKnK16C_g",
      "urlPreviewIsVisible": true,
      "commentIsVisible": true,
      "width": 235,
      "height": 48,
      "spaceId": "8B5r-G24hHzRdy9ca4x3-",
      "distanceFromOrigin": 954
    },
    {
      "id": "JvpWZ6MitV3fwqnVa_wsZ",
      "x": 344,
      "y": 916,
      "z": 1523,
      "name": "https://kinopio.club/journal-aKbPUalz4zHLqGwpDncDI",
      "frameId": null,
      "isRemoved": false,
      "linkToSpaceId": null,
      "commentIsVisible": false,
      "width": 235,
      "height": 63,
      "spaceId": "8B5r-G24hHzRdy9ca4x3-",
      "userId": "euGhpBrR9eBcjKnK16C_g",
      "distanceFromOrigin": 978
    },
    {
      "id": "jloLVWTCNkYORG8mpHgo5",
      "x": 694,
      "y": 715,
      "z": 1571,
      "name": "`Share → Invite` to collaborate with your friends or team ",
      "frameId": null,
      "isRemoved": false,
      "linkToSpaceId": null,
      "commentIsVisible": false,
      "width": 235,
      "height": 64,
      "spaceId": "8B5r-G24hHzRdy9ca4x3-",
      "userId": "euGhpBrR9eBcjKnK16C_g",
      "distanceFromOrigin": 996
    },
    {
      "id": "yM1xIKonuMJAiRWFZ_6rD",
      "x": 378,
      "y": 960,
      "z": 1524,
      "name": "https://kinopio.club/research-ZHoXccPyfmTu7FMueXUEP",
      "frameId": null,
      "isRemoved": false,
      "linkToSpaceId": null,
      "commentIsVisible": false,
      "width": 235,
      "height": 63,
      "spaceId": "8B5r-G24hHzRdy9ca4x3-",
      "userId": "euGhpBrR9eBcjKnK16C_g",
      "distanceFromOrigin": 1032
    },
    {
      "id": "5ujez5ncplTe_n5SR2eKX",
      "x": 694,
      "y": 790,
      "z": 1570,
      "name": "Desktop and mobile apps",
      "frameId": 0,
      "userId": "euGhpBrR9eBcjKnK16C_g",
      "urlPreviewIsVisible": true,
      "commentIsVisible": true,
      "width": 196,
      "height": 32,
      "spaceId": "8B5r-G24hHzRdy9ca4x3-",
      "distanceFromOrigin": 1052
    },
    {
      "id": "2hI9DeWreOzNb5HzrYrhb",
      "x": 1013,
      "y": 299,
      "z": 1417,
      "name": "https://kinopio.club/pop-up-shop-u9XxpuIzz2_LvQUAayl65 https://us-east-1.linodeobjects.com/kinopio-uploads/sxgcwhE5WoypHFn58JF5u/hand-made-patch.webp",
      "linkToSpaceId": null,
      "frameId": 0,
      "userId": "euGhpBrR9eBcjKnK16C_g",
      "urlPreviewIsVisible": true,
      "commentIsVisible": true,
      "width": 235,
      "height": 235,
      "spaceId": "8B5r-G24hHzRdy9ca4x3-",
      "distanceFromOrigin": 1056
    },
    {
      "id": "RRW_TkdIVtcEZPucDaatF",
      "x": 694,
      "y": 834,
      "z": 1569,
      "name": "Create, edit, and export your data with the API\nhttps://help.kinopio.club/api?hidden=true/",
      "frameId": 0,
      "userId": "euGhpBrR9eBcjKnK16C_g",
      "urlPreviewIsVisible": false,
      "commentIsVisible": true,
      "width": 235,
      "height": 47,
      "spaceId": "8B5r-G24hHzRdy9ca4x3-",
      "distanceFromOrigin": 1085,
      "urlPreviewUrl": "https://help.kinopio.club/api/",
      "urlPreviewTitle": "Kinopio API",
      "urlPreviewDescription": "Help site for Kinopio, the spatial thinking tool for new ideas and hard problems.",
      "urlPreviewImage": "",
      "urlPreviewFavicon": "https://help.kinopio.club/favicon.ico"
    },
    {
      "id": "9ALCuS28BsIbkr1JNfMYe",
      "x": 414,
      "y": 1007,
      "z": 1525,
      "name": "https://kinopio.club/mood-board-GgDOqKvEEzTA93EYmAZrn",
      "frameId": null,
      "isRemoved": false,
      "linkToSpaceId": null,
      "commentIsVisible": false,
      "width": 235,
      "height": 63,
      "spaceId": "8B5r-G24hHzRdy9ca4x3-",
      "userId": "euGhpBrR9eBcjKnK16C_g",
      "distanceFromOrigin": 1089
    },
    {
      "id": "HBI6rhtCpq4VeeasCAxOL",
      "x": 951,
      "y": 638,
      "z": 1587,
      "name": "[[Tip]] this card uses [[Tags]]",
      "frameId": 0,
      "userId": "euGhpBrR9eBcjKnK16C_g",
      "urlPreviewIsVisible": true,
      "commentIsVisible": true,
      "width": 217,
      "height": 33,
      "spaceId": "8B5r-G24hHzRdy9ca4x3-",
      "distanceFromOrigin": 1145
    },
    {
      "id": "3jxuXpdMggbenKDy3HvTP",
      "x": 967,
      "y": 805,
      "z": 1545,
      "name": "Collapsable comments (())",
      "frameId": 0,
      "isRemoved": false,
      "linkToSpaceId": null,
      "commentIsVisible": false,
      "width": 107,
      "height": 34,
      "spaceId": "8B5r-G24hHzRdy9ca4x3-",
      "userId": "euGhpBrR9eBcjKnK16C_g",
      "distanceFromOrigin": 1258
    }
  ],
  "connections": [
    {
      "id": "DgcEqrEcHqAq5Bdy4SAV0",
      "startCardId": "vHmOyLdtdZYYhP6fDSw9q",
      "endCardId": "CJJjlflWfieRV5GzpE9bW",
      "path": "m323,302 q90,40 35,112",
      "labelIsVisible": true,
      "spaceId": "49vML-ycQCP0U1zHZSxsX",
      "userId": "euGhpBrR9eBcjKnK16C_g",
      "connectionTypeId": "slt7x8xXMEAdHwkL0gUxa",
      "distanceFromOrigin": 442
    },
    {
      "id": "dqAU0OjbUTnjRYSM-HLv9",
      "startCardId": "CJJjlflWfieRV5GzpE9bW",
      "endCardId": "eduWHR0rqzT7KNZoxEq7A",
      "path": "m358,414 q90,40 0,73",
      "labelIsVisible": false,
      "spaceId": "8B5r-G24hHzRdy9ca4x3-",
      "userId": "euGhpBrR9eBcjKnK16C_g",
      "connectionTypeId": "slt7x8xXMEAdHwkL0gUxa",
      "distanceFromOrigin": 547
    },
    {
      "id": "cNe9-0JAYrSU9dREEbaGs",
      "startCardId": "eduWHR0rqzT7KNZoxEq7A",
      "endCardId": "CnODP7HgI_eeczBxGCaub",
      "path": "m358,487 q90,40 350,-369",
      "labelIsVisible": false,
      "spaceId": "8B5r-G24hHzRdy9ca4x3-",
      "userId": "euGhpBrR9eBcjKnK16C_g",
      "connectionTypeId": "slt7x8xXMEAdHwkL0gUxa",
      "distanceFromOrigin": 604
    },
    {
      "id": "QyLdN3EdDhlvfOyNF9UhJ",
      "startCardId": "uVMbWMqcXxXubI38hfurw",
      "endCardId": "BXy5f5rFWdgVS8YOdbvDO",
      "path": "m330,683 q90,40 128,162",
      "labelIsVisible": false,
      "spaceId": "8B5r-G24hHzRdy9ca4x3-",
      "userId": "euGhpBrR9eBcjKnK16C_g",
      "connectionTypeId": "rar1XGlDe9Wi4NMVtiA0S",
      "distanceFromOrigin": 759
    },
    {
      "id": "RxpcQnhcNUviB5S7FDJGP",
      "startCardId": "uVMbWMqcXxXubI38hfurw",
      "endCardId": "yM1xIKonuMJAiRWFZ_6rD",
      "path": "m330,683 q90,40 265,293",
      "labelIsVisible": false,
      "spaceId": "8B5r-G24hHzRdy9ca4x3-",
      "userId": "euGhpBrR9eBcjKnK16C_g",
      "connectionTypeId": "rar1XGlDe9Wi4NMVtiA0S",
      "distanceFromOrigin": 759
    },
    {
      "id": "AYgx7qHq11YuaqMSXVWe5",
      "startCardId": "uVMbWMqcXxXubI38hfurw",
      "endCardId": "dxXlCQ0nVrJWF-wm31dht",
      "path": "m330,683 q90,40 184,207",
      "labelIsVisible": true,
      "spaceId": "8B5r-G24hHzRdy9ca4x3-",
      "userId": "euGhpBrR9eBcjKnK16C_g",
      "connectionTypeId": "rar1XGlDe9Wi4NMVtiA0S",
      "distanceFromOrigin": 759
    },
    {
      "id": "ZUXqBrwZCweAnX6ryp6NS",
      "startCardId": "uVMbWMqcXxXubI38hfurw",
      "endCardId": "9ALCuS28BsIbkr1JNfMYe",
      "path": "m330,683 q90,40 301,340",
      "labelIsVisible": false,
      "spaceId": "8B5r-G24hHzRdy9ca4x3-",
      "userId": "euGhpBrR9eBcjKnK16C_g",
      "connectionTypeId": "rar1XGlDe9Wi4NMVtiA0S",
      "distanceFromOrigin": 759
    },
    {
      "id": "PtwN6j7ju55j0sypCsSH6",
      "startCardId": "uVMbWMqcXxXubI38hfurw",
      "endCardId": "JvpWZ6MitV3fwqnVa_wsZ",
      "path": "m330,683 q90,40 231,249",
      "labelIsVisible": false,
      "spaceId": "8B5r-G24hHzRdy9ca4x3-",
      "userId": "euGhpBrR9eBcjKnK16C_g",
      "connectionTypeId": "rar1XGlDe9Wi4NMVtiA0S",
      "distanceFromOrigin": 759
    },
    {
      "id": "rMXdK_Z9J-Nxyin84kBO7",
      "startCardId": "_QI-_MDbK7oZzxcbFUb3d",
      "endCardId": "JSXhmb1Fc-9Fau-qq7h32",
      "path": "m808,498 q90,40 103,173",
      "spaceId": "8B5r-G24hHzRdy9ca4x3-",
      "userId": "euGhpBrR9eBcjKnK16C_g",
      "connectionTypeId": "4RG28SXjOYQRuLA8Zab1D",
      "distanceFromOrigin": 949
    },
    {
      "id": "I72wHA1Hk30kp0NJUH4lh",
      "startCardId": "JSXhmb1Fc-9Fau-qq7h32",
      "endCardId": "jloLVWTCNkYORG8mpHgo5",
      "path": "m911,671 q90,40 0,60",
      "spaceId": "8B5r-G24hHzRdy9ca4x3-",
      "userId": "euGhpBrR9eBcjKnK16C_g",
      "connectionTypeId": "4RG28SXjOYQRuLA8Zab1D",
      "distanceFromOrigin": 1128
    },
    {
      "startCardId": "jloLVWTCNkYORG8mpHgo5",
      "endCardId": "5ujez5ncplTe_n5SR2eKX",
      "path": "m911,731 q90,40 -39,75",
      "id": "I2uxds7HmaCSd5afISUj8",
      "spaceId": "8B5r-G24hHzRdy9ca4x3-",
      "userId": "euGhpBrR9eBcjKnK16C_g",
      "connectionTypeId": "4RG28SXjOYQRuLA8Zab1D",
      "distanceFromOrigin": 1164
    },
    {
      "startCardId": "5ujez5ncplTe_n5SR2eKX",
      "endCardId": "RRW_TkdIVtcEZPucDaatF",
      "path": "m872,806 q90,40 39,44",
      "id": "cEzeMzQjOhGK5JUphMayW",
      "spaceId": "8B5r-G24hHzRdy9ca4x3-",
      "userId": "qSsfZtCrq-np7lttQYbb1",
      "connectionTypeId": "4RG28SXjOYQRuLA8Zab1D",
      "distanceFromOrigin": 1184
    }
  ],
  "connectionTypes": [
    {
      "id": "slt7x8xXMEAdHwkL0gUxa",
      "name": "How to Use",
      "color": "#7bee9f",
      "spaceId": "1",
      "userId": "euGhpBrR9eBcjKnK16C_g"
    },
    {
      "id": "rar1XGlDe9Wi4NMVtiA0S",
      "name": "Examples",
      "color": "#ffca99",
      "spaceId": "1",
      "userId": "euGhpBrR9eBcjKnK16C_g"
    },
    {
      "id": "4RG28SXjOYQRuLA8Zab1D",
      "name": "Try These",
      "color": "#d0a1ed",
      "spaceId": "1",
      "userId": "euGhpBrR9eBcjKnK16C_g"
    }
  ],
  "cacheDate": 1643066006351,
  "removedCards": [],
  "originSpaceId": "OyZvnvMO419R00oT4nOrK",
  "tags": [
    {
      "id": "oIafCLh99BMuACUAndRo7",
      "name": "Pricing",
      "color": "#adffc7",
      "cardId": "r2m6p5rYy_wlF3Ao8yQK5",
      "spaceId": "8B5r-G24hHzRdy9ca4x3-"
    },
    {
      "name": "Tags",
      "id": "JgzE3Zx5D4WKik5h-tlRv",
      "color": "#fcc4f6",
      "cardId": "JSXhmb1Fc-9Fau-qq7h32",
      "spaceId": "8B5r-G24hHzRdy9ca4x3-"
    },
    {
      "name": "Tip",
      "id": "Tor5m9I2EwE_2B97tosfy",
      "color": "#fcfc8f",
      "cardId": "HBI6rhtCpq4VeeasCAxOL",
      "spaceId": "8B5r-G24hHzRdy9ca4x3-"
    },
    {
      "name": "Tags",
      "id": "FIJbW8-5gpNYtKBWFDK30",
      "color": "#fcc4f6",
      "cardId": "HBI6rhtCpq4VeeasCAxOL",
      "spaceId": "8B5r-G24hHzRdy9ca4x3-"
    }
  ],
  "backgroundTint": "",
  "userId": "euGhpBrR9eBcjKnK16C_g",
  "isRemoved": false
}